Workbook

Sheet Daily Report & WIP
S1: AREA BANJARMASIN
H2: SELLING OUT BY MTD | K2: SELLING OUT BY MONTH | N2: SELLING OUT BY VALUE | S2: NURUL (JOINT DATE 1 Juli 2026) | X2: KHORUNISA (JOINT DATE 4 MEI 2026) | AC2: HERLISA (JOINT DATE 2 Desember 2025) | AH2: NUR (JOINT PER TANGGAL 14 AGUSTUS 2026)
A3: REGION | B3: AREA | C3: NAMA TOKO | E3: NAMA SPG | F3: JOINT DATE | G3: HK | H3: TARGET BY HK | I3: ACTUAL BY HK | J3: ACV BY HK (%) | K3: TARGET BY MONTH | L3: ACTUAL BY MONTH | M3: ACV BY MONTH (%) | N3: TOTAL VALUE (Rp) | O3: AVRG PER DAY | S3: Tanggal | T3: STATUS ABSENSI | U3: Selling (pcs) | V3: Value (Rp) | X3: Tanggal | Y3: STATUS ABSENSI | Z3: Selling (pcs) | AA3: Value (Rp) | AC3: Tanggal | AD3: STATUS ABSENSI | AE3: Selling (pcs) | AF3: Value (Rp) | AH3: Tanggal | AI3: STATUS ABSENSI | AJ3: Selling (pcs) | AK3: Value (Rp) | AM3: WIP DI BULAN AGUSTUS 1-31 (UPDATE DATA 1-17 AGUSTUS 2026)
S4: 46235 | T4: 1 | U4: 72 | V4: 432000 | X4: 46235 | Y4: 1 | Z4: 48 | AA4: 288000 | AC4: 46235 | AD4: 1 | AE4: 120 | AF4: 720000 | AH4: 46204 | AJ4: 24 | AK4: 168000 | AM4: AREA | AN4: NAMA | AO4: TARGET BY HK | AP4: ACTUAL BY HK | AQ4: ACCH BY ACTUAL (%) | AR4: ACH | AV4: AVERAGE | AZ4: TARGET BY MONTH | BA4: ACTUAL BY MONTH | BB4: ACCHV BY MONTH (%) | BC4: SELLING BY VALUE (Rp) | BD4: AVRG PER DAY | BE4: RATIO | BF4: GAJI ACTUAL BY HK | BG4: GAJI BY HK | BH4: GAP KARTON PER DAY | BI4: GAP CAN PER DAY | BJ4: TARGET VALUE | BK4: NEEDS VALUE | BL4: GAP RATIO | BM4: KOMITMEN RATIO | BN4: TARGET PER CAN 100% | BO4: TARGET PER KARTON 100% | BP4: TARGET 100% | BQ4: SISA 100% | BR4: SISA KARTON KE 100% | BS4: Joint Date
A5: 4 | B5: Banjarmasin | C5: Farez Barokah | E5: Nurul Agatha | F5: 1 Juli 2026 | G5: =SUM(T4:T34) -> 12 | H5: =G5*120 -> 1440 | I5: =SUM(U4:U34) -> 816 | J5: =I5/H5 -> 0.56666667 | K5: 3240 | L5: =SUM(I5) -> 816 | M5: =L5/K5 -> 0.25185185 | N5: =SUM(V4:V33) -> 4896000 | O5: =L5/G5 -> 68 | S5: 46236 | T5: OFF | X5: 46236 | Y5: OFF | AC5: 46236 | AD5: OFF | AH5: 46205 | AR5: W1 | AS5: W2 | AT5: W3 | AU5: W4 | AV5: W1 | AW5: W2 | AX5: W3 | AY5: W4
A6: 4 | B6: Banjarmasin | C6: yeyen/ibak | E6: Herlisa | F6: 2 Desember 2025 | G6: =SUM(AD4:AD33) -> 13 | H6: =G6*120 -> 1560 | I6: =SUM(AE4:AE33) -> 1272 | J6: =I6/H6 -> 0.81538462 | K6: 3240 | L6: =SUM(I6) -> 1272 | M6: =L6/K6 -> 0.39259259 | N6: =SUM(AF4:AF33) -> 7632000 | O6: =L6/G6 -> 97.846154 | S6: 46237 | T6: IZIN | X6: 46237 | Y6: 1 | Z6: 120 | AA6: 720000 | AC6: 46237 | AD6: 1 | AE6: 96 | AF6: 576000 | AH6: 46206 | AJ6: 24 | AK6: 144000 | AM6: BANJARMASIN | AN6: Nurul | AO6: 24 | AP6: =COUNTIF(T4:T34,1) -> 12 | AQ6: =IFERROR(AP6/AO6,0) -> 0.5 | AR6: =SUM(U4:U10) -> 312 | AS6: =SUM(U11:U17) -> 432 | AT6: =SUM(U18:U24) -> 72 | AU6: =SUM(U25:U34) -> 0 | AV6: =IFERROR(SUM(U4:U10)/COUNTIF(T4:T10,1),0) -> 62.4 | AW6: =IFERROR(SUM(U11:U17)/COUNTIF(T11:T17,1),0) -> 72 | AX6: =IFERROR(SUM(U18:U24)/COUNTIF(T18:T24,1),0) -> 72 | AY6: =IFERROR(SUM(U25:U34)/COUNTIF(T25:T34,1),0) -> 0 | AZ6: =3240 -> 3240 | BA6: =SUM(U4:U34) -> 816 | BB6: =IFERROR(BA6/AZ6,0) -> 0.25185185 | BC6: =SUM(V4:V34) -> 4896000 | BD6: =IFERROR(BA6/AP6,0) -> 68 | BE6: =IFERROR(BF6/BC6,0) -> 0.41607843 | BF6: =BG6*AP6 -> 2037120 | BG6: 169760 | BH6: =IFERROR(MAX(AZ6-BA6,0)/24/MAX(AO6-AP6,1),0) -> 8.4166667 | BI6: =IFERROR(MAX(AZ6-BA6,0)/MAX(AO6-AP6,1),0) -> 202 | BJ6: =IFERROR(26*BG6/BM6,0) -> 16347259 | BK6: =MAX(BJ6-BC6,0) -> 11451259 | BL6: =BE6-BM6 -> 0.14607843 | BM6: 0.27 | BN6: =IFERROR(MAX(BP6-BA6,0)/MAX(AO6-AP6,1),0) -> 202 | BO6: =BN6/24 -> 8.4166667 | BP6: =3240 -> 3240 | BQ6: =MAX(BP6-BA6,0) -> 2424 | BR6: =BQ6/24 -> 101 | BS6: 46204
A7: 4 | B7: Banjarmasin | C7: Saniah | E7: Khoirunisa | F7: 4 Mei 2026 | G7: =SUM(Y4:Y34) -> 12 | H7: =G7*120 -> 1440 | I7: =SUM(Z4:Z33) -> 1536 | J7: =I7/H7 -> 1.0666667 | K7: 3240 | L7: =SUM(I7) -> 1536 | M7: =L7/K7 -> 0.47407407 | N7: =SUM(AA4:AA33) -> 9196000 | O7: =L7/G7 -> 128 | S7: 46238 | T7: 1 | U7: 72 | V7: 432000 | X7: 46238 | Y7: 1 | Z7: 168 | AA7: 1008000 | AC7: 46238 | AD7: 1 | AE7: 168 | AF7: 1008000 | AH7: 46207 | AJ7: 24 | AK7: 144000 | AN7: Khoirunisa | AO7: 24 | AP7: =COUNTIF(Y4:Y34,1) -> 12 | AQ7: =IFERROR(AP7/AO7,0) -> 0.5 | AR7: =SUM(Z4:Z10) -> 888 | AS7: =SUM(Z11:Z17) -> 456 | AT7: =SUM(Z18:Z24) -> 192 | AU7: =SUM(Z25:Z34) -> 0 | AV7: =IFERROR(SUM(Z4:Z10)/COUNTIF(Y4:Y10,1),0) -> 148 | AW7: =IFERROR(SUM(Z11:Z17)/COUNTIF(Y11:Y17,1),0) -> 114 | AX7: =IFERROR(SUM(Z18:Z24)/COUNTIF(Y18:Y24,1),0) -> 96 | AY7: =IFERROR(SUM(Z25:Z34)/COUNTIF(Y25:Y34,1),0) -> 0 | AZ7: =3240 -> 3240 | BA7: =SUM(Z4:Z34) -> 1536 | BB7: =IFERROR(BA7/AZ7,0) -> 0.47407407 | BC7: =SUM(AA4:AA34) -> 9196000 | BD7: =IFERROR(BA7/AP7,0) -> 128 | BE7: =IFERROR(BF7/BC7,0) -> 0.2215224 | BF7: =BG7*AP7 -> 2037120 | BG7: 169760 | BH7: =IFERROR(MAX(AZ7-BA7,0)/24/MAX(AO7-AP7,1),0) -> 5.9166667 | BI7: =IFERROR(MAX(AZ7-BA7,0)/MAX(AO7-AP7,1),0) -> 142 | BJ7: =IFERROR(26*BG7/BM7,0) -> 16347259 | BK7: =MAX(BJ7-BC7,0) -> 7151259.3 | BL7: =BE7-BM7 -> -0.048477599 | BM7: 0.27 | BN7: =IFERROR(MAX(BP7-BA7,0)/MAX(AO7-AP7,1),0) -> 142 | BO7: =BN7/24 -> 5.9166667 | BP7: =3240 -> 3240 | BQ7: =MAX(BP7-BA7,0) -> 1704 | BR7: =BQ7/24 -> 71 | BS7: 46146
A8: 4 | B8: Banjarmasin | C8: Toko Ahim | E8: Nur | F8: 2 Juni 2026 | G8: =SUM(AI4:AI34) -> 2 | H8: =G8*120 -> 240 | I8: =SUM(AJ4:AJ33) -> 396 | J8: =I8/H8 -> 1.65 | K8: 3240 | L8: =SUM(I8) -> 396 | M8: =L8/K8 -> 0.12222222 | N8: =SUM(AK4:AK33) -> 2400000 | O8: =L8/G8 -> 198 | S8: 46239 | T8: 1 | U8: 48 | V8: 288000 | X8: 46239 | Y8: 1 | Z8: 192 | AA8: 1152000 | AC8: 46239 | AD8: 1 | AE8: 96 | AF8: 576000 | AH8: 46208 | AJ8: 48 | AK8: 288000 | AN8: Herlisa | AO8: 24 | AP8: =COUNTIF(AD4:AD34,1) -> 13 | AQ8: =IFERROR(AP8/AO8,0) -> 0.54166667 | AR8: =SUM(AE4:AE10) -> 648 | AS8: =SUM(AE11:AE17) -> 528 | AT8: =SUM(AE18:AE24) -> 96 | AU8: =SUM(AE25:AE34) -> 0 | AV8: =IFERROR(SUM(AE4:AE10)/COUNTIF(AD4:AD10,1),0) -> 108 | AW8: =IFERROR(SUM(AE11:AE17)/COUNTIF(AD11:AD17,1),0) -> 88 | AX8: =IFERROR(SUM(AE18:AE24)/COUNTIF(AD18:AD24,1),0) -> 96 | AY8: =IFERROR(SUM(AE25:AE34)/COUNTIF(AD25:AD34,1),0) -> 0 | AZ8: =3240 -> 3240 | BA8: =SUM(AE4:AE34) -> 1272 | BB8: =IFERROR(BA8/AZ8,0) -> 0.39259259 | BC8: =SUM(AF4:AF34) -> 7632000 | BD8: =IFERROR(BA8/AP8,0) -> 97.846154 | BE8: =IFERROR(BF8/BC8,0) -> 0.28916143 | BF8: =BG8*AP8 -> 2206880 | BG8: 169760 | BH8: =IFERROR(MAX(AZ8-BA8,0)/24/MAX(AO8-AP8,1),0) -> 7.4545455 | BI8: =IFERROR(MAX(AZ8-BA8,0)/MAX(AO8-AP8,1),0) -> 178.90909 | BJ8: =IFERROR(26*BG8/BM8,0) -> 16347259 | BK8: =MAX(BJ8-BC8,0) -> 8715259.3 | BL8: =BE8-BM8 -> 0.019161426 | BM8: 0.27 | BN8: =IFERROR(MAX(BP8-BA8,0)/MAX(AO8-AP8,1),0) -> 178.90909 | BO8: =BN8/24 -> 7.4545455 | BP8: =3240 -> 3240 | BQ8: =MAX(BP8-BA8,0) -> 1968 | BR8: =BQ8/24 -> 82 | BS8: 45993
A9: TOTAL BANJARMASIN | G9: =SUM(G5:G8) -> 39 | H9: =SUM(H5:H8) -> 4680 | I9: =SUM(I5:I8) -> 4020 | J9: =I9/H9 -> 0.85897436 | K9: =SUM(K5:K8) -> 12960 | L9: =SUM(L5:L8) -> 4020 | M9: =L9/K9 -> 0.31018519 | N9: =SUM(N5:N8) -> 24124000 | O9: =I9/G9 -> 103.07692 | S9: 46240 | T9: 1 | U9: 72 | V9: 432000 | X9: 46240 | Y9: 1 | Z9: 216 | AA9: 1296000 | AC9: 46240 | AD9: 1 | AE9: 96 | AF9: 576000 | AH9: 46209 | AJ9: 36 | AK9: 216000 | AN9: Nur | AO9: 24 | AP9: =COUNTIF(AI4:AI34,1) -> 2 | AQ9: =IFERROR(AP9/AO9,0) -> 0.083333333 | AR9: =SUM(AJ4:AJ10) -> 252 | AS9: =SUM(AJ11:AJ17) -> 72 | AT9: =SUM(AJ18:AJ24) -> 72 | AU9: =SUM(AJ25:AJ34) -> 0 | AV9: =IFERROR(SUM(AJ4:AJ10)/COUNTIF(AI4:AI10,1),0) -> 0 | AW9: =IFERROR(SUM(AJ11:AJ17)/COUNTIF(AI11:AI17,1),0) -> 72 | AX9: =IFERROR(SUM(AJ18:AJ24)/COUNTIF(AI18:AI24,1),0) -> 72 | AY9: =IFERROR(SUM(AJ25:AJ34)/COUNTIF(AI25:AI34,1),0) -> 0 | AZ9: =3240 -> 3240 | BA9: =SUM(AJ4:AJ34) -> 396 | BB9: =IFERROR(BA9/AZ9,0) -> 0.12222222 | BC9: =SUM(AK4:AK34) -> 2400000 | BD9: =IFERROR(BA9/AP9,0) -> 198 | BE9: =IFERROR(BF9/BC9,0) -> 0.14146667 | BF9: =BG9*AP9 -> 339520 | BG9: 169760 | BH9: =IFERROR(MAX(AZ9-BA9,0)/24/MAX(AO9-AP9,1),0) -> 5.3863636 | BI9: =IFERROR(MAX(AZ9-BA9,0)/MAX(AO9-AP9,1),0) -> 129.27273 | BJ9: =IFERROR(26*BG9/BM9,0) -> 16347259 | BK9: =MAX(BJ9-BC9,0) -> 13947259 | BL9: =BE9-BM9 -> -0.12853333 | BM9: 0.27 | BN9: =IFERROR(MAX(BP9-BA9,0)/MAX(AO9-AP9,1),0) -> 129.27273 | BO9: =BN9/24 -> 5.3863636 | BP9: =3240 -> 3240 | BQ9: =MAX(BP9-BA9,0) -> 2844 | BR9: =BQ9/24 -> 118.5 | BS9: 46248
S10: 46241 | T10: 1 | U10: 48 | V10: 288000 | X10: 46241 | Y10: 1 | Z10: 144 | AA10: 864000 | AC10: 46241 | AD10: 1 | AE10: 72 | AF10: 432000 | AH10: 46210 | AJ10: 96 | AK10: 576000 | AM10: GRAND TOTAL BANJARMASIN | AO10: =SUM(AO6:AO9) -> 96 | AP10: =SUM(AP6:AP9) -> 39 | AQ10: =IFERROR(AP10/AO10,0) -> 0.40625 | AR10: =SUM(AR6:AR9) -> 2100 | AS10: =SUM(AS6:AS9) -> 1488 | AT10: =SUM(AT6:AT9) -> 432 | AU10: =SUM(AU6:AU9) -> 0 | AV10: =IFERROR(AR10/(COUNTIF(T4:T10,1)+COUNTIF(Y4:Y10,1)+COUNTIF(AD4:AD10,1)+COUNTIF(AI4:AI10,1)),0) -> 123.52941 | AW10: =IFERROR(AS10/(COUNTIF(T11:T17,1)+COUNTIF(Y11:Y17,1)+COUNTIF(AD11:AD17,1)+COUNTIF(AI11:AI17,1)),0) -> 87.529412 | AX10: =IFERROR(AT10/(COUNTIF(T18:T24,1)+COUNTIF(Y18:Y24,1)+COUNTIF(AD18:AD24,1)+COUNTIF(AI18:AI24,1)),0) -> 86.4 | AY10: =IFERROR(AU10/(COUNTIF(T25:T34,1)+COUNTIF(Y25:Y34,1)+COUNTIF(AD25:AD34,1)+COUNTIF(AI25:AI34,1)),0) -> 0 | AZ10: =SUM(AZ6:AZ9) -> 12960 | BA10: =SUM(BA6:BA9) -> 4020 | BB10: =IFERROR(BA10/AZ10,0) -> 0.31018519 | BC10: =SUM(BC6:BC9) -> 24124000 | BD10: =IFERROR(BA10/AP10,0) -> 103.07692 | BE10: =IFERROR(BF10/BC10,0) -> 0.27444205 | BF10: =SUM(BF6:BF9) -> 6620640 | BG10: 169760 | BH10: =IFERROR(MAX(AZ10-BA10,0)/24/MAX(AO10-AP10,1),0) -> 6.5350877 | BI10: =IFERROR(MAX(AZ10-BA10,0)/MAX(AO10-AP10,1),0) -> 156.84211 | BJ10: =SUM(BJ6:BJ9) -> 65389037 | BK10: =MAX(BJ10-BC10,0) -> 41265037 | BL10: =BE10-BM10 -> 0.0044420494 | BM10: 0.27 | BN10: =IFERROR(MAX(BP10-BA10,0)/MAX(AO10-AP10,1),0) -> 156.84211 | BO10: =BN10/24 -> 6.5350877 | BP10: =SUM(BP6:BP9) -> 12960 | BQ10: =MAX(BP10-BA10,0) -> 8940 | BR10: =BQ10/24 -> 372.5
A11: Issue/Insight : | S11: 46242 | T11: 1 | U11: 72 | V11: 432000 | X11: 46242 | Y11: 1 | Z11: 144 | AA11: 864000 | AC11: 46242 | AD11: 1 | AE11: 96 | AF11: 576000 | AH11: 46211 | AJ11: 24 | AK11: 144000 | AM11: BALIKPAPAN | AN11: Grace | AO11: 24 | AP11: =COUNTIF(AD40:AD70,1) -> 13 | AQ11: =IFERROR(AP11/AO11,0) -> 0.54166667 | AR11: =SUM(AE40:AE46) -> 192 | AS11: =SUM(AE47:AE53) -> 240 | AT11: =SUM(AE54:AE60) -> 48 | AU11: =SUM(AE61:AE70) -> 0 | AV11: =IFERROR(SUM(AE40:AE46)/COUNTIF(AD40:AD46,1),0) -> 38.4 | AW11: =IFERROR(SUM(AE47:AE53)/COUNTIF(AD47:AD53,1),0) -> 40 | AX11: =IFERROR(SUM(AE54:AE60)/COUNTIF(AD54:AD60,1),0) -> 24 | AY11: =IFERROR(SUM(AE61:AE70)/COUNTIF(AD61:AD70,1),0) -> 0 | AZ11: =3240 -> 3240 | BA11: =SUM(AE40:AE70) -> 480 | BB11: =IFERROR(BA11/AZ11,0) -> 0.14814815 | BC11: =SUM(AF40:AF70) -> 2894400 | BD11: =IFERROR(BA11/AP11,0) -> 36.923077 | BE11: =IFERROR(BF11/BC11,0) -> 0.76260468 | BF11: =BG11*AP11 -> 2207283 | BG11: 169791 | BH11: =IFERROR(MAX(AZ11-BA11,0)/24/MAX(AO11-AP11,1),0) -> 10.454545 | BI11: =IFERROR(MAX(AZ11-BA11,0)/MAX(AO11-AP11,1),0) -> 250.90909 | BJ11: =IFERROR(26*BG11/BM11,0) -> 14715220 | BK11: =MAX(BJ11-BC11,0) -> 11820820 | BL11: =BE11-BM11 -> 0.46260468 | BM11: 0.3 | BN11: =IFERROR(MAX(BP11-BA11,0)/MAX(AO11-AP11,1),0) -> 250.90909 | BO11: =BN11/24 -> 10.454545 | BP11: =3240 -> 3240 | BQ11: =MAX(BP11-BA11,0) -> 2760 | BR11: =BQ11/24 -> 115 | BS11: 46204
A12: 1. SPG atas nama Herlisa izin | S12: 46243 | T12: OFF | X12: 46243 | Y12: OFF | AC12: 46243 | AD12: OFF | AH12: 46212 | AN12: Rami | AO12: 24 | AP12: =COUNTIF(AI40:AI70,1) -> 14 | AQ12: =IFERROR(AP12/AO12,0) -> 0.58333333 | AR12: =SUM(AJ40:AJ46) -> 240 | AS12: =SUM(AJ47:AJ53) -> 264 | AT12: =SUM(AJ54:AJ60) -> 168 | AU12: =SUM(AJ61:AJ70) -> 0 | AV12: =IFERROR(SUM(AJ40:AJ46)/COUNTIF(AI40:AI46,1),0) -> 48 | AW12: =IFERROR(SUM(AJ47:AJ53)/COUNTIF(AI47:AI53,1),0) -> 44 | AX12: =IFERROR(SUM(AJ54:AJ60)/COUNTIF(AI54:AI60,1),0) -> 56 | AY12: =IFERROR(SUM(AJ61:AJ70)/COUNTIF(AI61:AI70,1),0) -> 0 | AZ12: =3240 -> 3240 | BA12: =SUM(AJ40:AJ70) -> 672 | BB12: =IFERROR(BA12/AZ12,0) -> 0.20740741 | BC12: =SUM(AK40:AK70) -> 3952800 | BD12: =IFERROR(BA12/AP12,0) -> 48 | BE12: =IFERROR(BF12/BC12,0) -> 0.6013646 | BF12: =BG12*AP12 -> 2377074 | BG12: 169791 | BH12: =IFERROR(MAX(AZ12-BA12,0)/24/MAX(AO12-AP12,1),0) -> 10.7 | BI12: =IFERROR(MAX(AZ12-BA12,0)/MAX(AO12-AP12,1),0) -> 256.8 | BJ12: =IFERROR(26*BG12/BM12,0) -> 14715220 | BK12: =MAX(BJ12-BC12,0) -> 10762420 | BL12: =BE12-BM12 -> 0.3013646 | BM12: 0.3 | BN12: =IFERROR(MAX(BP12-BA12,0)/MAX(AO12-AP12,1),0) -> 256.8 | BO12: =BN12/24 -> 10.7 | BP12: =3240 -> 3240 | BQ12: =MAX(BP12-BA12,0) -> 2568 | BR12: =BQ12/24 -> 107 | BS12: 46174
A13: 2. Sebagian Toko/Retailer under grosir masih banyak stock | S13: 46244 | T13: 1 | U13: 72 | V13: 432000 | X13: 46244 | Y13: 1 | Z13: 120 | AA13: 720000 | AC13: 46244 | AD13: 1 | AE13: 96 | AF13: 576000 | AH13: 46213 | AM13: GRAND TOTAL BALIKPAPAN | AO13: =SUM(AO11:AO12) -> 48 | AP13: =SUM(AP11:AP12) -> 27 | AQ13: =IFERROR(AP13/AO13,0) -> 0.5625 | AR13: =SUM(AR11:AR12) -> 432 | AS13: =SUM(AS11:AS12) -> 504 | AT13: =SUM(AT11:AT12) -> 216 | AU13: =SUM(AU11:AU12) -> 0 | AV13: =IFERROR(AR13/(COUNTIF(AD40:AD46,1)+COUNTIF(AI40:AI46,1)),0) -> 43.2 | AW13: =IFERROR(AS13/(COUNTIF(AD47:AD53,1)+COUNTIF(AI47:AI53,1)),0) -> 42 | AX13: =IFERROR(AT13/(COUNTIF(AD54:AD60,1)+COUNTIF(AI54:AI60,1)),0) -> 43.2 | AY13: =IFERROR(AU13/(COUNTIF(AD61:AD70,1)+COUNTIF(AI61:AI70,1)),0) -> 0 | AZ13: =SUM(AZ11:AZ12) -> 6480 | BA13: =SUM(BA11:BA12) -> 1152 | BB13: =IFERROR(BA13/AZ13,0) -> 0.17777778 | BC13: =SUM(BC11:BC12) -> 6847200 | BD13: =IFERROR(BA13/AP13,0) -> 42.666667 | BE13: =IFERROR(BF13/BC13,0) -> 0.66952287 | BF13: =SUM(BF11:BF12) -> 4584357 | BG13: 169791 | BH13: =IFERROR(MAX(AZ13-BA13,0)/24/MAX(AO13-AP13,1),0) -> 10.571429 | BI13: =IFERROR(MAX(AZ13-BA13,0)/MAX(AO13-AP13,1),0) -> 253.71429 | BJ13: =SUM(BJ11:BJ12) -> 29430440 | BK13: =MAX(BJ13-BC13,0) -> 22583240 | BL13: =BE13-BM13 -> 0.36952287 | BM13: 0.3 | BN13: =IFERROR(MAX(BP13-BA13,0)/MAX(AO13-AP13,1),0) -> 253.71429 | BO13: =BN13/24 -> 10.571429 | BP13: =SUM(BP11:BP12) -> 6480 | BQ13: =MAX(BP13-BA13,0) -> 5328 | BR13: =BQ13/24 -> 222
A14: 3. SPG atas nama IKA Resign | S14: 46245 | T14: 1 | U14: 72 | V14: 432000 | X14: 46245 | Y14: IZIN | AC14: 46245 | AD14: 1 | AE14: 96 | AF14: 576000 | AH14: 46214 | AM14: PALANGKARAYA | AN14: Fani Febriani | AO14: 24 | AP14: =COUNTIF(T83:T113,1) -> 14 | AQ14: =IFERROR(AP14/AO14,0) -> 0.58333333 | AR14: =SUM(U83:U89) -> 354 | AS14: =SUM(U90:U96) -> 413 | AT14: =SUM(U97:U103) -> 168 | AU14: =SUM(U104:U113) -> 0 | AV14: =IFERROR(SUM(U83:U89)/COUNTIF(T83:T89,1),0) -> 59 | AW14: =IFERROR(SUM(U90:U96)/COUNTIF(T90:T96,1),0) -> 68.833333 | AX14: =IFERROR(SUM(U97:U103)/COUNTIF(T97:T103,1),0) -> 84 | AY14: =IFERROR(SUM(U104:U113)/COUNTIF(T104:T113,1),0) -> 0 | AZ14: =3240 -> 3240 | BA14: =SUM(U83:U113) -> 935 | BB14: =IFERROR(BA14/AZ14,0) -> 0.28858025 | BC14: =SUM(V83:V113) -> 5368000 | BD14: =IFERROR(BA14/AP14,0) -> 66.785714 | BE14: =IFERROR(BF14/BC14,0) -> 0.42957936 | BF14: =BG14*AP14 -> 2305982 | BG14: 164713 | BH14: =IFERROR(MAX(AZ14-BA14,0)/24/MAX(AO14-AP14,1),0) -> 9.6041667 | BI14: =IFERROR(MAX(AZ14-BA14,0)/MAX(AO14-AP14,1),0) -> 230.5 | BJ14: =IFERROR(26*BG14/BM14,0) -> 15861252 | BK14: =MAX(BJ14-BC14,0) -> 10493252 | BL14: =BE14-BM14 -> 0.15957936 | BM14: 0.27 | BN14: =IFERROR(MAX(BP14-BA14,0)/MAX(AO14-AP14,1),0) -> 230.5 | BO14: =BN14/24 -> 9.6041667 | BP14: =3240 -> 3240 | BQ14: =MAX(BP14-BA14,0) -> 2305 | BR14: =BQ14/24 -> 96.041667 | BS14: 46018
A15: 4. terdapat harga Rp.4.500 di toko di area Banjarmasin tengah | S15: 46246 | T15: 1 | U15: 72 | V15: 432000 | X15: 46246 | Y15: IZIN | AC15: 46246 | AD15: 1 | AE15: 72 | AF15: 432000 | AH15: 46215 | AN15: Siska | AO15: 24 | AP15: =COUNTIF(Y83:Y113,1) -> 14 | AQ15: =IFERROR(AP15/AO15,0) -> 0.58333333 | AR15: =SUM(Z83:Z89) -> 410 | AS15: =SUM(Z90:Z96) -> 466 | AT15: =SUM(Z97:Z103) -> 120 | AU15: =SUM(Z104:Z113) -> 0 | AV15: =IFERROR(SUM(Z83:Z89)/COUNTIF(Y83:Y89,1),0) -> 68.333333 | AW15: =IFERROR(SUM(Z90:Z96)/COUNTIF(Y90:Y96,1),0) -> 77.666667 | AX15: =IFERROR(SUM(Z97:Z103)/COUNTIF(Y97:Y103,1),0) -> 60 | AY15: =IFERROR(SUM(Z104:Z113)/COUNTIF(Y104:Y113,1),0) -> 0 | AZ15: =3240 -> 3240 | BA15: =SUM(Z83:Z113) -> 996 | BB15: =IFERROR(BA15/AZ15,0) -> 0.30740741 | BC15: =SUM(AA83:AA113) -> 5976000 | BD15: =IFERROR(BA15/AP15,0) -> 71.142857 | BE15: =IFERROR(BF15/BC15,0) -> 0.38587383 | BF15: =BG15*AP15 -> 2305982 | BG15: 164713 | BH15: =IFERROR(MAX(AZ15-BA15,0)/24/MAX(AO15-AP15,1),0) -> 9.35 | BI15: =IFERROR(MAX(AZ15-BA15,0)/MAX(AO15-AP15,1),0) -> 224.4 | BJ15: =IFERROR(26*BG15/BM15,0) -> 15861252 | BK15: =MAX(BJ15-BC15,0) -> 9885251.9 | BL15: =BE15-BM15 -> 0.11587383 | BM15: 0.27 | BN15: =IFERROR(MAX(BP15-BA15,0)/MAX(AO15-AP15,1),0) -> 224.4 | BO15: =BN15/24 -> 9.35 | BP15: =3240 -> 3240 | BQ15: =MAX(BP15-BA15,0) -> 2244 | BR15: =BQ15/24 -> 93.5 | BS15: 46120
S16: 46247 | T16: 1 | U16: 72 | V16: 432000 | X16: 46247 | Y16: 1 | Z16: 96 | AA16: 576000 | AC16: 46247 | AD16: 1 | AE16: 96 | AF16: 576000 | AH16: 46216 | AM16: GRAND TOTAL PALANGKARAYA | AO16: =SUM(AO14:AO15) -> 48 | AP16: =SUM(AP14:AP15) -> 28 | AQ16: =IFERROR(AP16/AO16,0) -> 0.58333333 | AR16: =SUM(AR14:AR15) -> 764 | AS16: =SUM(AS14:AS15) -> 879 | AT16: =SUM(AT14:AT15) -> 288 | AU16: =SUM(AU14:AU15) -> 0 | AV16: =IFERROR(AR16/(COUNTIF(T83:T89,1)+COUNTIF(Y83:Y89,1)),0) -> 63.666667 | AW16: =IFERROR(AS16/(COUNTIF(T90:T96,1)+COUNTIF(Y90:Y96,1)),0) -> 73.25 | AX16: =IFERROR(AT16/(COUNTIF(T97:T103,1)+COUNTIF(Y97:Y103,1)),0) -> 72 | AY16: =IFERROR(AU16/(COUNTIF(T104:T113,1)+COUNTIF(Y104:Y113,1)),0) -> 0 | AZ16: =SUM(AZ14:AZ15) -> 6480 | BA16: =SUM(BA14:BA15) -> 1931 | BB16: =IFERROR(BA16/AZ16,0) -> 0.29799383 | BC16: =SUM(BC14:BC15) -> 11344000 | BD16: =IFERROR(BA16/AP16,0) -> 68.964286 | BE16: =IFERROR(BF16/BC16,0) -> 0.40655536 | BF16: =SUM(BF14:BF15) -> 4611964 | BG16: 164713 | BH16: =IFERROR(MAX(AZ16-BA16,0)/24/MAX(AO16-AP16,1),0) -> 9.4770833 | BI16: =IFERROR(MAX(AZ16-BA16,0)/MAX(AO16-AP16,1),0) -> 227.45 | BJ16: =SUM(BJ14:BJ15) -> 31722504 | BK16: =MAX(BJ16-BC16,0) -> 20378504 | BL16: =BE16-BM16 -> 0.13655536 | BM16: 0.27 | BN16: =IFERROR(MAX(BP16-BA16,0)/MAX(AO16-AP16,1),0) -> 227.45 | BO16: =BN16/24 -> 9.4770833 | BP16: =SUM(BP14:BP15) -> 6480 | BQ16: =MAX(BP16-BA16,0) -> 4549 | BR16: =BQ16/24 -> 189.54167
A17: Action Plan: | S17: 46248 | T17: 1 | U17: 72 | V17: 432000 | X17: 46248 | Y17: 1 | Z17: 96 | AA17: 576000 | AC17: 46248 | AD17: 1 | AE17: 72 | AF17: 432000 | AH17: 46217 | AI17: 1 | AJ17: 48 | AK17: 288000 | AM17: SAMARINDA | AN17: Fitriani | AO17: 24 | AP17: =COUNTIF(T40:T70,1) -> 13 | AQ17: =IFERROR(AP17/AO17,0) -> 0.54166667 | AR17: =SUM(U40:U46) -> 240 | AS17: =SUM(U47:U53) -> 456 | AT17: =SUM(U54:U60) -> 168 | AU17: =SUM(U61:U70) -> 0 | AV17: =IFERROR(SUM(U40:U46)/COUNTIF(T40:T46,1),0) -> 48 | AW17: =IFERROR(SUM(U47:U53)/COUNTIF(T47:T53,1),0) -> 76 | AX17: =IFERROR(SUM(U54:U60)/COUNTIF(T54:T60,1),0) -> 84 | AY17: =IFERROR(SUM(U61:U70)/COUNTIF(T61:T70,1),0) -> 0 | AZ17: =3240 -> 3240 | BA17: =SUM(U40:U70) -> 864 | BB17: =IFERROR(BA17/AZ17,0) -> 0.26666667 | BC17: =SUM(V40:V70) -> 5616000 | BD17: =IFERROR(BA17/AP17,0) -> 66.461538 | BE17: =IFERROR(BF17/BC17,0) -> 0.4043588 | BF17: =BG17*AP17 -> 2270879 | BG17: 174683 | BH17: =IFERROR(MAX(AZ17-BA17,0)/24/MAX(AO17-AP17,1),0) -> 9 | BI17: =IFERROR(MAX(AZ17-BA17,0)/MAX(AO17-AP17,1),0) -> 216 | BJ17: =IFERROR(26*BG17/BM17,0) -> 15139193 | BK17: =MAX(BJ17-BC17,0) -> 9523193.3 | BL17: =BE17-BM17 -> 0.1043588 | BM17: 0.3 | BN17: =IFERROR(MAX(BP17-BA17,0)/MAX(AO17-AP17,1),0) -> 216 | BO17: =BN17/24 -> 9 | BP17: =3240 -> 3240 | BQ17: =MAX(BP17-BA17,0) -> 2376 | BR17: =BQ17/24 -> 99 | BS17: 46060
A18: 1. Untuk toko stok masih banyak: jangan push ambil banyak, cukup order kecil 3–6 can + bantu display biar stok lama cepat jalan, lalu follow up H+3. | S18: 46249 | T18: 1 | U18: 72 | V18: 432000 | X18: 46249 | Y18: 1 | Z18: 120 | AA18: 700000 | AC18: 46249 | AD18: 1 | AE18: 96 | AF18: 576000 | AH18: 46218 | AI18: 1 | AJ18: 72 | AK18: 432000 | AN18: Desi Susanti | AO18: 24 | AP18: =COUNTIF(Y40:Y70,1) -> 14 | AQ18: =IFERROR(AP18/AO18,0) -> 0.58333333 | AR18: =SUM(Z40:Z46) -> 312 | AS18: =SUM(Z47:Z53) -> 384 | AT18: =SUM(Z54:Z60) -> 120 | AU18: =SUM(Z61:Z70) -> 0 | AV18: =IFERROR(SUM(Z40:Z46)/COUNTIF(Y40:Y46,1),0) -> 52 | AW18: =IFERROR(SUM(Z47:Z53)/COUNTIF(Y47:Y53,1),0) -> 64 | AX18: =IFERROR(SUM(Z54:Z60)/COUNTIF(Y54:Y60,1),0) -> 60 | AY18: =IFERROR(SUM(Z61:Z70)/COUNTIF(Y61:Y70,1),0) -> 0 | AZ18: =3240 -> 3240 | BA18: =SUM(Z40:Z70) -> 816 | BB18: =IFERROR(BA18/AZ18,0) -> 0.25185185 | BC18: =SUM(AA40:AA70) -> 5112000 | BD18: =IFERROR(BA18/AP18,0) -> 58.285714 | BE18: =IFERROR(BF18/BC18,0) -> 0.47839632 | BF18: =BG18*AP18 -> 2445562 | BG18: 174683 | BH18: =IFERROR(MAX(AZ18-BA18,0)/24/MAX(AO18-AP18,1),0) -> 10.1 | BI18: =IFERROR(MAX(AZ18-BA18,0)/MAX(AO18-AP18,1),0) -> 242.4 | BJ18: =IFERROR(26*BG18/BM18,0) -> 15139193 | BK18: =MAX(BJ18-BC18,0) -> 10027193 | BL18: =BE18-BM18 -> 0.17839632 | BM18: 0.3 | BN18: =IFERROR(MAX(BP18-BA18,0)/MAX(AO18-AP18,1),0) -> 242.4 | BO18: =BN18/24 -> 10.1 | BP18: =3240 -> 3240 | BQ18: =MAX(BP18-BA18,0) -> 2424 | BR18: =BQ18/24 -> 101 | BS18: 46073
A19: 2. SPG fokus edukasi dan sampling saat stay di Outlet | S19: 46250 | T19: OFF | X19: 46250 | Y19: 1 | Z19: 72 | AA19: 432000 | AC19: 46250 | AD19: OFF | AH19: 46219 | AM19: GRAND TOTAL SAMARINDA | AO19: =SUM(AO17:AO18) -> 48 | AP19: =SUM(AP17:AP18) -> 27 | AQ19: =IFERROR(AP19/AO19,0) -> 0.5625 | AR19: =SUM(AR17:AR18) -> 552 | AS19: =SUM(AS17:AS18) -> 840 | AT19: =SUM(AT17:AT18) -> 288 | AU19: =SUM(AU17:AU18) -> 0 | AV19: =IFERROR(AR19/(COUNTIF(T40:T46,1)+COUNTIF(Y40:Y46,1)),0) -> 50.181818 | AW19: =IFERROR(AS19/(COUNTIF(T47:T53,1)+COUNTIF(Y47:Y53,1)),0) -> 70 | AX19: =IFERROR(AT19/(COUNTIF(T54:T60,1)+COUNTIF(Y54:Y60,1)),0) -> 72 | AY19: =IFERROR(AU19/(COUNTIF(T61:T70,1)+COUNTIF(Y61:Y70,1)),0) -> 0 | AZ19: =SUM(AZ17:AZ18) -> 6480 | BA19: =SUM(BA17:BA18) -> 1680 | BB19: =IFERROR(BA19/AZ19,0) -> 0.25925926 | BC19: =SUM(BC17:BC18) -> 10728000 | BD19: =IFERROR(BA19/AP19,0) -> 62.222222 | BE19: =IFERROR(BF19/BC19,0) -> 0.43963842 | BF19: =SUM(BF17:BF18) -> 4716441 | BG19: 174683 | BH19: =IFERROR(MAX(AZ19-BA19,0)/24/MAX(AO19-AP19,1),0) -> 9.5238095 | BI19: =IFERROR(MAX(AZ19-BA19,0)/MAX(AO19-AP19,1),0) -> 228.57143 | BJ19: =SUM(BJ17:BJ18) -> 30278387 | BK19: =MAX(BJ19-BC19,0) -> 19550387 | BL19: =BE19-BM19 -> 0.13963842 | BM19: 0.3 | BN19: =IFERROR(MAX(BP19-BA19,0)/MAX(AO19-AP19,1),0) -> 228.57143 | BO19: =BN19/24 -> 9.5238095 | BP19: =SUM(BP17:BP18) -> 6480 | BQ19: =MAX(BP19-BA19,0) -> 4800 | BR19: =BQ19/24 -> 200
A20: 3. Fokus untuk jalin hubungan dengan toko-toko meminta no wa pihak toko jika dari toko barang masih ada | S20: 46251 | T20: IZIN | X20: 46251 | Y20: LIBUR | AC20: 46251 | AD20: LIBUR | AH20: 46220 | AM20: MAKASSAR | AN20: Amelia | AO20: 24 | AP20: =COUNTIF(T119:T149,1) -> 16 | AQ20: =IFERROR(AP20/AO20,0) -> 0.66666667 | AR20: =SUM(U119:U125) -> 204 | AS20: =SUM(U126:U132) -> 151 | AT20: =SUM(U133:U139) -> 132 | AU20: =SUM(U140:U149) -> 0 | AV20: =IFERROR(SUM(U119:U125)/COUNTIF(T119:T125,1),0) -> 34 | AW20: =IFERROR(SUM(U126:U132)/COUNTIF(T126:T132,1),0) -> 25.166667 | AX20: =IFERROR(SUM(U133:U139)/COUNTIF(T133:T139,1),0) -> 33 | AY20: =IFERROR(SUM(U140:U149)/COUNTIF(T140:T149,1),0) -> 0 | AZ20: =3240 -> 3240 | BA20: =SUM(U119:U149) -> 487 | BB20: =IFERROR(BA20/AZ20,0) -> 0.15030864 | BC20: =SUM(V119:V149) -> 3251000 | BD20: =IFERROR(BA20/AP20,0) -> 30.4375 | BE20: =IFERROR(BF20/BC20,0) -> 0.89081267 | BF20: =BG20*AP20 -> 2896032 | BG20: 181002 | BH20: =IFERROR(MAX(AZ20-BA20,0)/24/MAX(AO20-AP20,1),0) -> 14.338542 | BI20: =IFERROR(MAX(AZ20-BA20,0)/MAX(AO20-AP20,1),0) -> 344.125 | BJ20: =IFERROR(26*BG20/BM20,0) -> 15686840 | BK20: =MAX(BJ20-BC20,0) -> 12435840 | BL20: =BE20-BM20 -> 0.59081267 | BM20: 0.3 | BN20: =IFERROR(MAX(BP20-BA20,0)/MAX(AO20-AP20,1),0) -> 344.125 | BO20: =BN20/24 -> 14.338542 | BP20: =3240 -> 3240 | BQ20: =MAX(BP20-BA20,0) -> 2753 | BR20: =BQ20/24 -> 114.70833 | BS20: 46057
S21: 46252 | X21: 46252 | AC21: 46252 | AH21: 46221 | AN21: Dira/Nadira | AO21: 24 | AP21: =COUNTIF(Y119:Y149,1) -> 13 | AQ21: =IFERROR(AP21/AO21,0) -> 0.54166667 | AR21: =SUM(Z119:Z125) -> 65 | AS21: =SUM(Z126:Z132) -> 47 | AT21: =SUM(Z133:Z139) -> 111 | AU21: =SUM(Z140:Z149) -> 0 | AV21: =IFERROR(SUM(Z119:Z125)/COUNTIF(Y119:Y125,1),0) -> 13 | AW21: =IFERROR(SUM(Z126:Z132)/COUNTIF(Y126:Y132,1),0) -> 11.75 | AX21: =IFERROR(SUM(Z133:Z139)/COUNTIF(Y133:Y139,1),0) -> 27.75 | AY21: =IFERROR(SUM(Z140:Z149)/COUNTIF(Y140:Y149,1),0) -> 0 | AZ21: =3240 -> 3240 | BA21: =SUM(Z119:Z149) -> 223 | BB21: =IFERROR(BA21/AZ21,0) -> 0.06882716 | BC21: =SUM(AA119:AA149) -> 1226500 | BD21: =IFERROR(BA21/AP21,0) -> 17.153846 | BE21: =IFERROR(BF21/BC21,0) -> 1.9184884 | BF21: =BG21*AP21 -> 2353026 | BG21: 181002 | BH21: =IFERROR(MAX(AZ21-BA21,0)/24/MAX(AO21-AP21,1),0) -> 11.42803 | BI21: =IFERROR(MAX(AZ21-BA21,0)/MAX(AO21-AP21,1),0) -> 274.27273 | BJ21: =IFERROR(26*BG21/BM21,0) -> 15686840 | BK21: =MAX(BJ21-BC21,0) -> 14460340 | BL21: =BE21-BM21 -> 1.6184884 | BM21: 0.3 | BN21: =IFERROR(MAX(BP21-BA21,0)/MAX(AO21-AP21,1),0) -> 274.27273 | BO21: =BN21/24 -> 11.42803 | BP21: =3240 -> 3240 | BQ21: =MAX(BP21-BA21,0) -> 3017 | BR21: =BQ21/24 -> 125.70833 | BS21: 46175
S22: 46253 | X22: 46253 | AC22: 46253 | AH22: 46222 | AN22: Nurhijrah | AO22: 24 | AP22: =COUNTIF(AD119:AD149,1) -> 15 | AQ22: =IFERROR(AP22/AO22,0) -> 0.625 | AR22: =SUM(AE119:AE125) -> 183 | AS22: =SUM(AE126:AE132) -> 163 | AT22: =SUM(AE133:AE139) -> 129 | AU22: =SUM(AE140:AE149) -> 0 | AV22: =IFERROR(SUM(AE119:AE125)/COUNTIF(AD119:AD125,1),0) -> 30.5 | AW22: =IFERROR(SUM(AE126:AE132)/COUNTIF(AD126:AD132,1),0) -> 32.6 | AX22: =IFERROR(SUM(AE133:AE139)/COUNTIF(AD133:AD139,1),0) -> 32.25 | AY22: =IFERROR(SUM(AE140:AE149)/COUNTIF(AD140:AD149,1),0) -> 0 | AZ22: =3240 -> 3240 | BA22: =SUM(AE119:AE149) -> 475 | BB22: =IFERROR(BA22/AZ22,0) -> 0.14660494 | BC22: =SUM(AF119:AF149) -> 3063300 | BD22: =IFERROR(BA22/AP22,0) -> 31.666667 | BE22: =IFERROR(BF22/BC22,0) -> 0.88630888 | BF22: =BG22*AP22 -> 2715030 | BG22: 181002 | BH22: =IFERROR(MAX(AZ22-BA22,0)/24/MAX(AO22-AP22,1),0) -> 12.800926 | BI22: =IFERROR(MAX(AZ22-BA22,0)/MAX(AO22-AP22,1),0) -> 307.22222 | BJ22: =IFERROR(26*BG22/BM22,0) -> 15686840 | BK22: =MAX(BJ22-BC22,0) -> 12623540 | BL22: =BE22-BM22 -> 0.58630888 | BM22: 0.3 | BN22: =IFERROR(MAX(BP22-BA22,0)/MAX(AO22-AP22,1),0) -> 307.22222 | BO22: =BN22/24 -> 12.800926 | BP22: =3240 -> 3240 | BQ22: =MAX(BP22-BA22,0) -> 2765 | BR22: =BQ22/24 -> 115.20833 | BS22: 46235
H23: SELLING OUT BY MTD | K23: SELLING OUT BY MONTH | N23: SELLING OUT BY VALUE | S23: 46254 | X23: 46254 | AC23: 46254 | AH23: 46223 | AM23: GRAND TOTAL MAKASSAR | AO23: =SUM(AO20:AO22) -> 72 | AP23: =SUM(AP20:AP22) -> 44 | AQ23: =IFERROR(AP23/AO23,0) -> 0.61111111 | AR23: =SUM(AR20:AR22) -> 452 | AS23: =SUM(AS20:AS22) -> 361 | AT23: =SUM(AT20:AT22) -> 372 | AU23: =SUM(AU20:AU22) -> 0 | AV23: =IFERROR(AR23/(COUNTIF(T119:T125,1)+COUNTIF(Y119:Y125,1)+COUNTIF(AD119:AD125,1)),0) -> 26.588235 | AW23: =IFERROR(AS23/(COUNTIF(T126:T132,1)+COUNTIF(Y126:Y132,1)+COUNTIF(AD126:AD132,1)),0) -> 24.066667 | AX23: =IFERROR(AT23/(COUNTIF(T133:T139,1)+COUNTIF(Y133:Y139,1)+COUNTIF(AD133:AD139,1)),0) -> 31 | AY23: =IFERROR(AU23/(COUNTIF(T140:T149,1)+COUNTIF(Y140:Y149,1)+COUNTIF(AD140:AD149,1)),0) -> 0 | AZ23: =SUM(AZ20:AZ22) -> 9720 | BA23: =SUM(BA20:BA22) -> 1185 | BB23: =IFERROR(BA23/AZ23,0) -> 0.12191358 | BC23: =SUM(BC20:BC22) -> 7540800 | BD23: =IFERROR(BA23/AP23,0) -> 26.931818 | BE23: =IFERROR(BF23/BC23,0) -> 1.056133 | BF23: =SUM(BF20:BF22) -> 7964088 | BG23: 181002 | BH23: =IFERROR(MAX(AZ23-BA23,0)/24/MAX(AO23-AP23,1),0) -> 12.700893 | BI23: =IFERROR(MAX(AZ23-BA23,0)/MAX(AO23-AP23,1),0) -> 304.82143 | BJ23: =SUM(BJ20:BJ22) -> 47060520 | BK23: =MAX(BJ23-BC23,0) -> 39519720 | BL23: =BE23-BM23 -> 0.75613304 | BM23: 0.3 | BN23: =IFERROR(MAX(BP23-BA23,0)/MAX(AO23-AP23,1),0) -> 304.82143 | BO23: =BN23/24 -> 12.700893 | BP23: =SUM(BP20:BP22) -> 9720 | BQ23: =MAX(BP23-BA23,0) -> 8535 | BR23: =BQ23/24 -> 355.625
A24: REGION | B24: AREA | C24: NAMA TOKO | E24: NAMA SPG | F24: JOINT DATE | G24: HK | H24: TARGET BY HK | I24: ACTUAL BY HK | J24: ACV BY HK (%) | K24: TARGET BY MONTH | L24: ACTUAL BY MONTH | M24: ACV BY MONTH (%) | N24: TOTAL VALUE (Rp) | O24: AVRG PER DAY | S24: 46255 | X24: 46255 | AC24: 46255 | AH24: 46224 | AM24: MANADO | AN24: Dea | AO24: 24 | AP24: =COUNTIF(AD83:AD113,1) -> 13 | AQ24: =IFERROR(AP24/AO24,0) -> 0.54166667 | AR24: =SUM(AE83:AE89) -> 144 | AS24: =SUM(AE90:AE96) -> 174 | AT24: =SUM(AE97:AE103) -> 60 | AU24: =SUM(AE104:AE113) -> 0 | AV24: =IFERROR(SUM(AE83:AE89)/COUNTIF(AD83:AD89,1),0) -> 28.8 | AW24: =IFERROR(SUM(AE90:AE96)/COUNTIF(AD90:AD96,1),0) -> 29 | AX24: =IFERROR(SUM(AE97:AE103)/COUNTIF(AD97:AD103,1),0) -> 30 | AY24: =IFERROR(SUM(AE104:AE113)/COUNTIF(AD104:AD113,1),0) -> 0 | AZ24: =3240 -> 3240 | BA24: =SUM(AE83:AE113) -> 378 | BB24: =IFERROR(BA24/AZ24,0) -> 0.11666667 | BC24: =SUM(AF83:AF113) -> 2256000 | BD24: =IFERROR(BA24/AP24,0) -> 29.076923 | BE24: =IFERROR(BF24/BC24,0) -> 0.97121986 | BF24: =BG24*AP24 -> 2191072 | BG24: 168544 | BH24: =IFERROR(MAX(AZ24-BA24,0)/24/MAX(AO24-AP24,1),0) -> 10.840909 | BI24: =IFERROR(MAX(AZ24-BA24,0)/MAX(AO24-AP24,1),0) -> 260.18182 | BJ24: =IFERROR(26*BG24/BM24,0) -> 14607147 | BK24: =MAX(BJ24-BC24,0) -> 12351147 | BL24: =BE24-BM24 -> 0.67121986 | BM24: 0.3 | BN24: =IFERROR(MAX(BP24-BA24,0)/MAX(AO24-AP24,1),0) -> 260.18182 | BO24: =BN24/24 -> 10.840909 | BP24: =3240 -> 3240 | BQ24: =MAX(BP24-BA24,0) -> 2862 | BR24: =BQ24/24 -> 119.25 | BS24: 46157
S25: 46256 | X25: 46256 | AC25: 46256 | AH25: 46225 | AN25: Regina | AO25: 24 | AP25: =COUNTIF(AI83:AI113,1) -> 13 | AQ25: =IFERROR(AP25/AO25,0) -> 0.54166667 | AR25: =SUM(AJ83:AJ89) -> 177 | AS25: =SUM(AJ90:AJ96) -> 162 | AT25: =SUM(AJ97:AJ103) -> 35 | AU25: =SUM(AJ104:AJ113) -> 0 | AV25: =IFERROR(SUM(AJ83:AJ89)/COUNTIF(AI83:AI89,1),0) -> 29.5 | AW25: =IFERROR(SUM(AJ90:AJ96)/COUNTIF(AI90:AI96,1),0) -> 27 | AX25: =IFERROR(SUM(AK90:AK96)/COUNTIF(AJ90:AJ96,1),0) -> 0 | AY25: =IFERROR(SUM(AJ104:AJ113)/COUNTIF(AI104:AI113,1),0) -> 0 | AZ25: =3240 -> 3240 | BA25: =SUM(AJ83:AJ113) -> 374 | BB25: =IFERROR(BA25/AZ25,0) -> 0.1154321 | BC25: =SUM(AK83:AK113) -> 2244000 | BD25: =IFERROR(BA25/AP25,0) -> 28.769231 | BE25: =IFERROR(BF25/BC25,0) -> 0.97641355 | BF25: =BG25*AP25 -> 2191072 | BG25: 168544 | BH25: =IFERROR(MAX(AZ25-BA25,0)/24/MAX(AO25-AP25,1),0) -> 10.856061 | BI25: =IFERROR(MAX(AZ25-BA25,0)/MAX(AO25-AP25,1),0) -> 260.54545 | BJ25: =IFERROR(26*BG25/BM25,0) -> 14607147 | BK25: =MAX(BJ25-BC25,0) -> 12363147 | BL25: =BE25-BM25 -> 0.67641355 | BM25: 0.3 | BN25: =IFERROR(MAX(BP25-BA25,0)/MAX(AO25-AP25,1),0) -> 260.54545 | BO25: =BN25/24 -> 10.856061 | BP25: =3240 -> 3240 | BQ25: =MAX(BP25-BA25,0) -> 2866 | BR25: =BQ25/24 -> 119.41667 | BS25: 46188
A26: 4 | B26: Balikpapan | C26: Toko Perdana | E26: Rami | F26: 1 Juni 2026 | G26: =SUM(AI40:AI69) -> 14 | H26: =G26*120 -> 1680 | I26: =SUM(AJ40:AJ69) -> 672 | J26: =I26/H26 -> 0.4 | K26: 3240 | L26: =SUM(I26) -> 672 | M26: =L26/K26 -> 0.20740741 | N26: =SUM(AK40:AK70) -> 3952800 | O26: =I26/G26 -> 48 | S26: 46257 | X26: 46257 | AC26: 46257 | AH26: 46226 | AM26: GRAND TOTAL MANADO | AO26: =SUM(AO24:AO25) -> 48 | AP26: =SUM(AP24:AP25) -> 26 | AQ26: =IFERROR(AP26/AO26,0) -> 0.54166667 | AR26: =SUM(AR24:AR25) -> 321 | AS26: =SUM(AS24:AS25) -> 336 | AT26: =SUM(AT24:AT25) -> 95 | AU26: =SUM(AU24:AU25) -> 0 | AV26: =IFERROR(AR26/(COUNTIF(AD83:AD89,1)+COUNTIF(AI83:AI89,1)),0) -> 29.181818 | AW26: =IFERROR(AS26/(COUNTIF(AD90:AD96,1)+COUNTIF(AI90:AI96,1)),0) -> 28 | AX26: =IFERROR(AT26/(COUNTIF(AD97:AD103,1)+COUNTIF(AI97:AI103,1)),0) -> 31.666667 | AY26: =IFERROR(AU26/(COUNTIF(AD104:AD113,1)+COUNTIF(AI104:AI113,1)),0) -> 0 | AZ26: =SUM(AZ24:AZ25) -> 6480 | BA26: =SUM(BA24:BA25) -> 752 | BB26: =IFERROR(BA26/AZ26,0) -> 0.11604938 | BC26: =SUM(BC24:BC25) -> 4500000 | BD26: =IFERROR(BA26/AP26,0) -> 28.923077 | BE26: =IFERROR(BF26/BC26,0) -> 0.97380978 | BF26: =SUM(BF24:BF25) -> 4382144 | BG26: 168544 | BH26: =IFERROR(MAX(AZ26-BA26,0)/24/MAX(AO26-AP26,1),0) -> 10.848485 | BI26: =IFERROR(MAX(AZ26-BA26,0)/MAX(AO26-AP26,1),0) -> 260.36364 | BJ26: =SUM(BJ24:BJ25) -> 29214293 | BK26: =MAX(BJ26-BC26,0) -> 24714293 | BL26: =BE26-BM26 -> 0.67380978 | BM26: 0.3 | BN26: =IFERROR(MAX(BP26-BA26,0)/MAX(AO26-AP26,1),0) -> 260.36364 | BO26: =BN26/24 -> 10.848485 | BP26: =SUM(BP24:BP25) -> 6480 | BQ26: =MAX(BP26-BA26,0) -> 5728 | BR26: =BQ26/24 -> 238.66667
A27: 4 | B27: Balikpapan | C27: Toko Perdana | E27: Grace | F27: 1 Juli 2026 | G27: =SUM(AD40:AD69) -> 13 | H27: =G27*120 -> 1560 | I27: =SUM(AE40:AE71) -> 480 | J27: =I27/H27 -> 0.30769231 | K27: 3240 | L27: =SUM(I27) -> 480 | M27: =L27/K27 -> 0.14814815 | N27: =SUM(AF40:AF70) -> 2894400 | O27: =I27/G27 -> 36.923077 | S27: 46258 | X27: 46258 | AC27: 46258 | AH27: 46227 | AM27: GRAND TOTAL COVER | AO27: =SUM(AO10,AO13,AO16,AO19,AO23,AO26) -> 360 | AP27: =SUM(AP10,AP13,AP16,AP19,AP23,AP26) -> 191 | AQ27: =IFERROR(AP27/AO27,0) -> 0.53055556 | AR27: =SUM(AR10,AR13,AR16,AR19,AR23,AR26) -> 4621 | AS27: =SUM(AS10,AS13,AS16,AS19,AS23,AS26) -> 4408 | AT27: =SUM(AT10,AT13,AT16,AT19,AT23,AT26) -> 1691 | AU27: =SUM(AU10,AU13,AU16,AU19,AU23,AU26) -> 0 | AV27: =AVERAGE(AV10,AV13,AV16,AV19,AV23,AV26) -> 56.057992 | AW27: =AVERAGE(AW10,AW13,AW16,AW19,AW23,AW26) -> 54.141013 | AX27: =AVERAGE(AX10,AX13,AX16,AX19,AX23,AX26) -> 56.044444 | AY27: =AVERAGE(AY10,AY13,AY16,AY19,AY23,AY26) -> 0 | AZ27: =SUM(AZ10,AZ13,AZ16,AZ19,AZ23,AZ26) -> 48600 | BA27: =SUM(BA10,BA13,BA16,BA19,BA23,BA26) -> 10720 | BB27: =IFERROR(BA27/AZ27,0) -> 0.22057613 | BC27: =SUM(BC10,BC13,BC16,BC19,BC23,BC26) -> 65084000 | BD27: =IFERROR(BA27/AP27,0) -> 56.125654 | BE27: =IFERROR(BF27/BC27,0) -> 0.50518767 | BF27: =SUM(BF10,BF13,BF16,BF19,BF23,BF26) -> 32879634 | BH27: =IFERROR(MAX(AZ27-BA27,0)/24/MAX(AO27-AP27,1),0) -> 9.3392505 | BI27: =IFERROR(MAX(AZ27-BA27,0)/MAX(AO27-AP27,1),0) -> 224.14201 | BJ27: =SUM(BJ10,BJ13,BJ16,BJ19,BJ23,BJ26) -> 2.3309518e+08 | BK27: =MAX(BJ27-BC27,0) -> 1.6801118e+08 | BL27: =BE27-BM27 -> 0.21768619 | BM27: =((26*BG6)+(26*BG7)+(26*BG8)+(26*BG9)+(26*BG11)+(26*BG12)+(26*BG14)+(26*BG15)+(26*BG17)+(26*BG18)+(26*BG20)+(26*BG21)+(26*BG22)+(26*BG24)+(26*BG25))/BJ27 -> 0.28750147 | BN27: =IFERROR(MAX(BP27-BA27,0)/MAX(AO27-AP27,1),0) -> 224.14201 | BO27: =BN27/24 -> 9.3392505 | BP27: =SUM(BP10,BP13,BP16,BP19,BP23,BP26) -> 48600 | BQ27: =MAX(BP27-BA27,0) -> 37880 | BR27: =BQ27/24 -> 1578.3333
A28: TOTAL BALIKPAPAN | G28: =SUM(G26:G27) -> 27 | H28: =SUM(H26:H27) -> 3240 | I28: =SUM(I26:I27) -> 1152 | J28: =I28/H28 -> 0.35555556 | K28: =SUM(K26:K27) -> 6480 | L28: =SUM(L26:L27) -> 1152 | M28: =L28/K28 -> 0.17777778 | N28: =SUM(N26:N27) -> 6847200 | O28: =L28/G28 -> 42.666667 | S28: 46259 | X28: 46259 | AC28: 46259 | AH28: 46228
S29: 46260 | X29: 46260 | AC29: 46260 | AH29: 46229
H30: SELLING OUT BY MTD | K30: SELLING OUT BY MONTH | N30: SELLING OUT BY VALUE | S30: 46261 | X30: 46261 | AC30: 46261 | AH30: 46230
A31: REGION | B31: AREA | C31: NAMA TOKO | E31: NAMA SPG | F31: JOINT DATE | G31: HK | H31: TARGET BY HK | I31: ACTUAL BY HK | J31: ACV BY HK (%) | K31: TARGET BY MONTH | L31: ACTUAL BY MONTH | M31: ACV BY MONTH (%) | N31: TOTAL VALUE (Rp) | O31: AVRG PER DAY | S31: 46262 | X31: 46262 | AC31: 46262 | AH31: 46231
S32: 46263 | X32: 46263 | AC32: 46263 | AH32: 46232
A33: 4 | B33: Palangkaraya | C33: Toko Tanjung | E33: Fani Febriani | F33: 27 Desember 2025 | G33: =SUM(T83:T113) -> 14 | H33: =G33*120 -> 1680 | I33: =SUM(U83:U113) -> 935 | J33: =I33/H33 -> 0.55654762 | K33: 3240 | L33: =SUM(I33) -> 935 | M33: =L33/K33 -> 0.28858025 | N33: =SUM(V83:V112) -> 5368000 | O33: =L33/G33 -> 66.785714 | S33: 46264 | X33: 46264 | AC33: 46264 | AH33: 46233
A34: 4 | B34: Palangkaraya | C34: Toko H fathur | E34: Siska | F34: 8 April 2026 | G34: =SUM(Y83:Y113) -> 14 | H34: =G34*120 -> 1680 | I34: =SUM(Z83:Z113) -> 996 | J34: =I34/H34 -> 0.59285714 | K34: 3240 | L34: =SUM(I34) -> 996 | M34: =L34/K34 -> 0.30740741 | N34: =SUM(AA83:AA112) -> 5976000 | O34: =L34/G34 -> 71.142857 | S34: 46265 | X34: 46265 | AC34: 46265 | AH34: 46234
A35: TOTAL PALANGKARAYA | G35: =SUM(G33:G34) -> 28 | H35: =SUM(H33:H34) -> 3360 | I35: =SUM(I33:I34) -> 1931 | J35: =I35/H35 -> 0.57470238 | K35: =SUM(K33:K34) -> 6480 | L35: =SUM(L33:L34) -> 1931 | M35: =L35/K35 -> 0.29799383 | N35: =SUM(N33:N34) -> 11344000 | O35: =L35/G35 -> 68.964286
H37: SELLING OUT BY MTD | K37: SELLING OUT BY MONTH | N37: SELLING OUT BY VALUE | S37: AREA SAMARINDA | AC37: AREA BALIKPAPAN
A38: REGION | B38: AREA | C38: NAMA TOKO | E38: NAMA SPG | F38: JOINT DATE | G38: HK | H38: TARGET BY HK | I38: ACTUAL BY HK | J38: ACV BY HK (%) | K38: TARGET BY MONTH | L38: ACTUAL BY MONTH | M38: ACV BY MONTH (%) | N38: TOTAL VALUE (Rp) | O38: AVRG PER DAY | S38: FITRIANI (JOINT PER TANGGAL 7 FEBRUARI 2026) | X38: DESI SUSANTI (JOINT PER TANGGAL 20 FEBRUARI 2026) | AC38: GRACE (JOINT PER TANGGAL 1 JULI 2026) | AH38: RAMI (JOINT PER TANGGAL 1 JUNI 2026)
S39: Tanggal | T39: STATUS ABSENSI | U39: Selling (pcs) | V39: Value (Rp) | X39: Tanggal | Y39: STATUS ABSENSI | Z39: Selling (pcs) | AA39: Value (Rp) | AC39: Tanggal | AD39: STATUS ABSENSI | AE39: Selling (pcs) | AF39: Value (Rp) | AH39: Tanggal | AI39: STATUS ABSENSI | AJ39: Selling (pcs) | AK39: Value (Rp)
A40: 4 | B40: Samarinda | C40: Toko Alam Subur | E40: Fitriani | F40: 7 Februari 2026 | G40: =SUM(T40:T69) -> 13 | H40: =G40*120 -> 1560 | I40: =SUM(U40:U70) -> 864 | J40: =I40/H40 -> 0.55384615 | K40: 3240 | L40: =SUM(I40) -> 864 | M40: =L40/K40 -> 0.26666667 | N40: =SUM(V40:V69) -> 5616000 | O40: 93 | S40: 46235 | T40: OFF | X40: 46235 | Y40: 1 | AC40: 46235 | AD40: IZIN | AH40: 46235 | AI40: IZIN
A41: 4 | B41: Samarinda | C41: Toko Surya Indah | E41: Desi susanti | F41: 20 Februari 2026 | G41: =SUM(Y40:Y70) -> 14 | H41: =G41*96 -> 1344 | I41: =SUM(Z40:Z69) -> 816 | J41: =I41/H41 -> 0.60714286 | K41: 3240 | L41: =SUM(I41) -> 816 | M41: =L41/K41 -> 0.25185185 | N41: =SUM(AA40:AA69) -> 5112000 | O41: 85 | S41: 46236 | T41: OFF | X41: 46236 | Y41: OFF | AC41: 46236 | AD41: OFF | AH41: 46236 | AI41: OFF
A42: TOTAL SAMARINDA | G42: =SUM(G40:G41) -> 27 | H42: =SUM(H40:H41) -> 2904 | I42: =SUM(I40:I41) -> 1680 | J42: =I42/H42 -> 0.5785124 | K42: =SUM(K40:K41) -> 6480 | L42: =SUM(L40:L41) -> 1680 | M42: =L42/K42 -> 0.25925926 | N42: =SUM(N40:N41) -> 10728000 | O42: 89 | S42: 46237 | T42: 1 | U42: 24 | V42: 156000 | X42: 46237 | Y42: 1 | Z42: 72 | AA42: 432000 | AC42: 46237 | AD42: 1 | AE42: 24 | AF42: 156000 | AH42: 46237 | AI42: 1 | AJ42: 24 | AK42: 144000
S43: 46238 | T43: 1 | U43: 24 | V43: 156000 | X43: 46238 | Y43: 1 | Z43: 72 | AA43: 432000 | AC43: 46238 | AD43: 1 | AE43: 48 | AF43: 312000 | AH43: 46238 | AI43: 1 | AJ43: 48 | AK43: 288000
A44: Issue/Insight : | S44: 46239 | T44: 1 | U44: 72 | V44: 468000 | X44: 46239 | Y44: 1 | Z44: 48 | AA44: 288000 | AC44: 46239 | AD44: 1 | AE44: 48 | AF44: 288000 | AH44: 46239 | AI44: 1 | AJ44: 72 | AK44: 432000
A45: 1. stok toko masih tinggi, perputaran produk lambat, dan toko belum prioritas untuk tambah order ( Banjarmasin, Samarinda, dan Balikpapan) | S45: 46240 | T45: 1 | U45: 48 | V45: 312000 | X45: 46240 | Y45: 1 | Z45: 48 | AA45: 288000 | AC45: 46240 | AD45: 1 | AE45: 48 | AF45: 288000 | AH45: 46240 | AI45: 1 | AJ45: 72 | AK45: 432000
A46: 2. Beberapa outlet sudah di-cover sales atau motoris saat SPG Spreading, sehingga ruang closing SPG menjadi lebih terbatas (Banjarmasin, Samarinda, Balikpapan) | S46: 46241 | T46: 1 | U46: 72 | V46: 468000 | X46: 46241 | Y46: 1 | Z46: 72 | AA46: 432000 | AC46: 46241 | AD46: 1 | AE46: 24 | AF46: 144000 | AH46: 46241 | AI46: 1 | AJ46: 24 | AK46: 144000
A47: 3. Traffic toko masih rendah, cuaca hujan, dan jam operasional outlet tidak optimal (Balikpapan). | S47: 46242 | T47: 1 | U47: 72 | V47: 468000 | X47: 46242 | Y47: 1 | Z47: 72 | AA47: 432000 | AC47: 46242 | AD47: 1 | AE47: 24 | AF47: 144000 | AH47: 46242 | AI47: 1 | AJ47: 24 | AK47: 144000
A48: 4. Support sampling belum ada di Area Palangkaraya | S48: 46243 | T48: OFF | X48: 46243 | Y48: OFF | AC48: 46243 | AD48: OFF | AH48: 46243 | AI48: OFF
A49: 5. Sampling sudah terdistribusikan ke SPG di area Balikpapan | S49: 46244 | T49: 1 | U49: 96 | V49: 624000 | X49: 46244 | Y49: 1 | Z49: 48 | AA49: 312000 | AC49: 46244 | AD49: 1 | AE49: 48 | AF49: 288000 | AH49: 46244 | AI49: 1 | AJ49: 24 | AK49: 144000
A50: Action Plan: | S50: 46245 | T50: 1 | U50: 48 | V50: 312000 | X50: 46245 | Y50: 1 | Z50: 72 | AA50: 468000 | AC50: 46245 | AD50: 1 | AE50: 48 | AF50: 288000 | AH50: 46245 | AI50: 1 | AJ50: 48 | AK50: 288000
A51: 1. Prioritaskan kunjungan ke outlet yang masih memiliki peluang closing dan repeat order (Semua area). | S51: 46246 | T51: 1 | U51: 72 | V51: 468000 | X51: 46246 | Y51: 1 | Z51: 72 | AA51: 468000 | AC51: 46246 | AD51: 1 | AE51: 48 | AF51: 288000 | AH51: 46246 | AI51: 1 | AJ51: 72 | AK51: 432000
A52: 2. Terapkan booking order atau jadwal follow up yang jelas untuk outlet yang belum ambil barang hari ini (Semua area). | S52: 46247 | T52: 1 | U52: 96 | V52: 624000 | X52: 46247 | Y52: 1 | Z52: 72 | AA52: 468000 | AC52: 46247 | AD52: 1 | AE52: 48 | AF52: 288000 | AH52: 46247 | AI52: 1 | AJ52: 72 | AK52: 410400
A53: 3. Lakukan pengecekan ulang stok dan pergerakan barang pada outlet yang berulang kali menolak order (Banjarmasin, Samarinda, Balikpapan). | S53: 46248 | T53: 1 | U53: 72 | V53: 468000 | X53: 46248 | Y53: 1 | Z53: 48 | AA53: 312000 | AC53: 46248 | AD53: 1 | AE53: 24 | AF53: 136800 | AH53: 46248 | AI53: 1 | AJ53: 24 | AK53: 136800
A54: 4. Perkuat coaching SPG dalam handling objection terkait stok lama, slow moving, coverage sales, dan respon konsumen di outlet (Semua area). | S54: 46249 | T54: 1 | U54: 72 | V54: 468000 | X54: 46249 | Y54: 1 | Z54: 48 | AA54: 312000 | AC54: 46249 | AD54: 1 | AE54: 24 | AF54: 136800 | AH54: 46249 | AI54: 1 | AJ54: 24 | AK54: 136800
A55: 5. Atur kunjungan lebih awal agar peluang closing tidak hilang karena cuaca dan jam tutup outlet (Balikpapan). | S55: 46250 | T55: OFF | X55: 46250 | Y55: OFF | AC55: 46250 | AD55: OFF | AH55: 46250 | AI55: OFF
S56: 46251 | T56: LIBUR | X56: 46251 | Y56: LIBUR | AC56: 46251 | AD56: LIBUR | AH56: 46251 | AI56: 1 | AJ56: 72 | AK56: 410400
S57: 46252 | T57: 1 | U57: 96 | V57: 624000 | X57: 46252 | Y57: 1 | Z57: 72 | AA57: 468000 | AC57: 46252 | AD57: 1 | AE57: 24 | AF57: 136800 | AH57: 46252 | AI57: 1 | AJ57: 72 | AK57: 410400
S58: 46253 | X58: 46253 | AC58: 46253 | AH58: 46253
S59: 46254 | X59: 46254 | AC59: 46254 | AH59: 46254
S60: 46255 | X60: 46255 | AC60: 46255 | AH60: 46255
S61: 46256 | X61: 46256 | AC61: 46256 | AH61: 46256
S62: 46257 | X62: 46257 | AC62: 46257 | AH62: 46257
S63: 46258 | X63: 46258 | AC63: 46258 | AH63: 46258
S64: 46259 | X64: 46259 | AC64: 46259 | AH64: 46259
S65: 46260 | X65: 46260 | AC65: 46260 | AH65: 46260
S66: 46261 | X66: 46261 | AC66: 46261 | AH66: 46261
S67: 46262 | X67: 46262 | AC67: 46262 | AH67: 46262
S68: 46263 | X68: 46263 | AC68: 46263 | AH68: 46263
S69: 46264 | X69: 46264 | AC69: 46264 | AH69: 46264
S70: 46265 | X70: 46265 | AC70: 46265 | AH70: 46265
S80: AREA PALANGKARAYA | AC80: AREA MANADO
S81: FANI FEBRIANI (JOINT PER TANGGAL 27 DESEMBER 2025) | X81: SISKA (JOINT PER TANGGAL 8 APRIL 2026) | AC81: DEA (JOINT PER TANGGAL 15 MEI 2026) | AH81: REGINA (JOINT PER TANGGAL 15 JUNI 2026)
S82: Tanggal | T82: STATUS ABSENSI | U82: Selling (pcs) | V82: Value (Rp) | X82: Tanggal | Y82: STATUS ABSENSI | Z82: Selling (pcs) | AA82: Value (Rp) | AC82: Tanggal | AD82: STATUS ABSENSI | AE82: Selling (pcs) | AF82: Value (Rp) | AH82: Tanggal | AI82: STATUS ABSENSI | AJ82: Selling (pcs) | AK82: Value (Rp)
H83: SELLING OUT BY MTD | K83: SELLING OUT BY MONTH | N83: SELLING OUT BY VALUE | S83: 46235 | T83: 1 | U83: 72 | V83: 432000 | X83: 46235 | Y83: 1 | Z83: 48 | AA83: 288000 | AC83: 46235 | AD83: IZIN | AH83: 46235 | AI83: 1 | AJ83: 24 | AK83: 144000
A84: REGION | B84: AREA | C84: NAMA TOKO | E84: NAMA SPG | F84: JOINT DATE | G84: HK | H84: TARGET BY HK | I84: ACTUAL BY HK | J84: ACV BY HK (%) | K84: TARGET BY MONTH | L84: ACTUAL BY MONTH | M84: ACV BY MONTH (%) | N84: TOTAL VALUE (Rp) | O84: AVRG PER DAY | S84: 46236 | T84: 1 | U84: 48 | V84: 288000 | X84: 46236 | Y84: 1 | Z84: 72 | AA84: 432000 | AC84: 46236 | AD84: OFF | AH84: 46236 | AI84: OFF
S85: 46237 | T85: OFF | X85: 46237 | Y85: 1 | Z85: 72 | AA85: 432000 | AC85: 46237 | AD85: 1 | AE85: 24 | AF85: 144000 | AH85: 46237 | AI85: 1 | AJ85: 24 | AK85: 144000
A86: 4 | B86: Manado | C86: Kasih Setia | E86: Dea | F86: 46200 | G86: =SUM(AD83:AD112) -> 13 | H86: =G86*120 -> 1560 | I86: =SUM(AE83:AE112) -> 378 | J86: =I86/H86 -> 0.24230769 | K86: 3240 | L86: =SUM(I86) -> 378 | M86: =L86/K86 -> 0.11666667 | N86: =SUM(AF83:AF112) -> 2256000 | O86: =I86/G86 -> 29.076923 | S86: 46238 | T86: 1 | U86: 96 | V86: 576000 | X86: 46238 | Y86: 1 | Z86: 50 | AA86: 300000 | AC86: 46238 | AD86: 1 | AE86: 48 | AF86: 288000 | AH86: 46238 | AI86: 1 | AJ86: 51 | AK86: 306000
A87: 4 | B87: Manado | C87: Lovely Jaya | E87: Regina | F87: 46196 | G87: =SUM(AI83:AI112) -> 13 | H87: =G87*120 -> 1560 | I87: =SUM(AJ83:AJ112) -> 374 | J87: =I87/H87 -> 0.23974359 | K87: 3240 | L87: =SUM(I87) -> 374 | M87: =L87/K87 -> 0.1154321 | N87: =SUM(AK83:AK112) -> 2244000 | O87: =I87/G87 -> 28.769231 | S87: 46239 | T87: 1 | U87: 38 | V87: 228000 | X87: 46239 | Y87: 1 | Z87: 48 | AA87: 288000 | AC87: 46239 | AD87: 1 | AE87: 24 | AF87: 144000 | AH87: 46239 | AI87: 1 | AJ87: 30 | AK87: 180000
A88: TOTAL MANADO | G88: =SUM(G86:G87) -> 26 | H88: =SUM(H86) -> 1560 | I88: =SUM(I86) -> 378 | J88: =I88/H88 -> 0.24230769 | K88: 2304 | L88: =SUM(L86) -> 378 | M88: =L88/K88 -> 0.1640625 | N88: =SUM(N86) -> 2256000 | O88: =I88/G88 -> 14.538462 | S88: 46240 | T88: 1 | U88: 48 | V88: 288000 | X88: 46240 | Y88: OFF | AC88: 46240 | AD88: 1 | AE88: 24 | AF88: 144000 | AH88: 46240 | AI88: 1 | AJ88: 24 | AK88: 144000
S89: 46241 | T89: 1 | U89: 52 | V89: 364000 | X89: 46241 | Y89: 1 | Z89: 120 | AA89: 720000 | AC89: 46241 | AD89: 1 | AE89: 24 | AF89: 144000 | AH89: 46241 | AI89: 1 | AJ89: 24 | AK89: 144000
A90: Issue/Insight : | S90: 46242 | T90: 1 | U90: 96 | V90: 500000 | X90: 46242 | Y90: 1 | Z90: 48 | AA90: 288000 | AC90: 46242 | AD90: 1 | AE90: 48 | AF90: 288000 | AH90: 46242 | AI90: 1 | AJ90: 30 | AK90: 180000
A91: 1. Banyak toko menolak order karena stok masih ada/full | S91: 46243 | T91: 1 | U91: 72 | V91: 369000 | X91: 46243 | Y91: 1 | Z91: 72 | AA91: 432000 | AC91: 46243 | AD91: OFF | AH91: 46243 | AI91: OFF
A92: 2. Customer cenderung fokus beli sembako/keperluan harian, minuman jadi kurang prioritas. | S92: 46244 | T92: OFF | X92: 46244 | Y92: 1 | Z92: 96 | AA92: 576000 | AC92: 46244 | AD92: 1 | AE92: 24 | AF92: 144000 | AH92: 46244 | AI92: 1 | AJ92: 24 | AK92: 144000
A93: 3. Kebanyakan Lansia dan tidak biasa mengonsumsi minuman asam | S93: 46245 | T93: 1 | U93: 96 | V93: 500000 | X93: 46245 | Y93: 1 | Z93: 120 | AA93: 720000 | AC93: 46245 | AD93: 1 | AE93: 30 | AF93: 180000 | AH93: 46245 | AI93: 1 | AJ93: 30 | AK93: 180000
S94: 46246 | T94: 1 | U94: 39 | V94: 273000 | X94: 46246 | Y94: 1 | Z94: 58 | AA94: 348000 | AC94: 46246 | AD94: 1 | AE94: 24 | AF94: 132000 | AH94: 46246 | AI94: 1 | AJ94: 30 | AK94: 180000
A95: Action Plan: | S95: 46247 | T95: 1 | U95: 48 | V95: 246000 | X95: 46247 | Y95: OFF | AC95: 46247 | AD95: 1 | AE95: 24 | AF95: 144000 | AH95: 46247 | AI95: 1 | AJ95: 24 | AK95: 144000
A96: 1. Jalankan strategi “booking order” untuk toko yang stop order kedepannya | S96: 46248 | T96: 1 | U96: 62 | V96: 372000 | X96: 46248 | Y96: 1 | Z96: 72 | AA96: 432000 | AC96: 46248 | AD96: 1 | AE96: 24 | AF96: 144000 | AH96: 46248 | AI96: 1 | AJ96: 24 | AK96: 144000
A97: 2. SPG melakukan sampling sesuai segmentasi usia | S97: 46249 | T97: 1 | U97: 96 | V97: 500000 | X97: 46249 | Y97: 1 | Z97: 120 | AA97: 720000 | AC97: 46249 | AD97: 1 | AE97: 36 | AF97: 216000 | AH97: 46249 | AI97: 1 | AJ97: 35 | AK97: 210000
A98: 3. SPG Spreading ketika stokis sepi | S98: 46250 | T98: 1 | U98: 72 | V98: 432000 | X98: 46250 | Y98: 1 | AC98: 46250 | AD98: OFF | AH98: 46250 | AI98: OFF
A99: 4. SPG edukasi terkait produk extra joss ke konsumen/retail | S99: 46251 | T99: LIBUR | X99: 46251 | Y99: LIBUR | AC99: 46251 | AD99: LIBUR | AH99: 46251 | AI99: LIBUR
S100: 46252 | X100: 46252 | AC100: 46252 | AD100: 1 | AE100: 24 | AF100: 144000 | AH100: 46252 | AI100: OFF
S101: 46253 | X101: 46253 | AC101: 46253 | AH101: 46253
S102: 46254 | X102: 46254 | AC102: 46254 | AH102: 46254
S103: 46255 | X103: 46255 | AC103: 46255 | AH103: 46255
S104: 46256 | X104: 46256 | AC104: 46256 | AH104: 46256
S105: 46257 | X105: 46257 | AC105: 46257 | AH105: 46257
S106: 46258 | X106: 46258 | AC106: 46258 | AH106: 46258
S107: 46259 | X107: 46259 | AC107: 46259 | AH107: 46259
S108: 46260 | X108: 46260 | AC108: 46260 | AH108: 46260
S109: 46261 | X109: 46261 | AC109: 46261 | AH109: 46261
S110: 46262 | X110: 46262 | AC110: 46262 | AH110: 46262
...

Sheet HK
A1: PLANNING HK SPG AGUSTUS 2026 - POSISI 1-17 AGUSTUS
A2: Target 24 HK | 25 Agustus LIBUR | OFF Mingguan: semua SPG hari Minggu, Fani hari Senin, Siska hari Kamis
A4: AREA | B4: SPG | C4: HK ACTUAL 1-17 | D4: TARGET HK | E4: SISA HK | F4: 46252 | G4: 46253 | H4: 46254 | I4: 46255 | J4: 46256 | K4: 23/08/2026 (MINGGU) | L4: 46258 | M4: 46259 | N4: 46260 | O4: 46261 | P4: 46262 | Q4: 46263 | R4: 46264 | S4: 46265 | T4: PROYEKSI HK | U4: GAP HK | V4: STATUS
A5: Banjarmasin | B5: Nurul | C5: =COUNTIF('Daily Report & WIP'!T4:T20,1) -> 12 | D5: 24 | E5: =MAX(D5-C5,0) -> 12 | F5: =IF($E5>0,"KERJA","OFF TARGET") -> KERJA | G5: =IF(COUNTIF($F5:F5,"KERJA")<$E5,"KERJA","OFF TARGET") -> KERJA | H5: =IF(COUNTIF($F5:G5,"KERJA")<$E5,"KERJA","OFF TARGET") -> KERJA | I5: =IF(COUNTIF($F5:H5,"KERJA")<$E5,"KERJA","OFF TARGET") -> KERJA | J5: =IF(COUNTIF($F5:I5,"KERJA")<$E5,"KERJA","OFF TARGET") -> KERJA | K5: OFF | L5: =IF(COUNTIF($F5:K5,"KERJA")<$E5,"KERJA","OFF TARGET") -> KERJA | M5: LIBUR | N5: =IF(COUNTIF($F5:M5,"KERJA")<$E5,"KERJA","OFF TARGET") -> KERJA | O5: =IF(COUNTIF($F5:N5,"KERJA")<$E5,"KERJA","OFF TARGET") -> KERJA | P5: =IF(COUNTIF($F5:O5,"KERJA")<$E5,"KERJA","OFF TARGET") -> KERJA | Q5: =IF(COUNTIF($F5:P5,"KERJA")<$E5,"KERJA","OFF TARGET") -> KERJA | R5: OFF | S5: =IF(COUNTIF($F5:R5,"KERJA")<$E5,"KERJA","OFF TARGET") -> KERJA | T5: =C5+COUNTIF(F5:S5,"KERJA") -> 23 | U5: =D5-T5 -> 1 | V5: =IF(U5=0,"TARGET 24 HK TERCAPAI",IF(U5>0,"MASIH KURANG "&U5&" HK","LEBIH "&ABS(U5)&" HK")) -> MASIH KURANG 1 HK
A6: Banjarmasin | B6: Khoirunisa | C6: =COUNTIF('Daily Report & WIP'!Y4:Y20,1) -> 12 | D6: 24 | E6: =MAX(D6-C6,0) -> 12 | F6: =IF($E6>0,"KERJA","OFF TARGET") -> KERJA | G6: =IF(COUNTIF($F6:F6,"KERJA")<$E6,"KERJA","OFF TARGET") -> KERJA | H6: =IF(COUNTIF($F6:G6,"KERJA")<$E6,"KERJA","OFF TARGET") -> KERJA | I6: =IF(COUNTIF($F6:H6,"KERJA")<$E6,"KERJA","OFF TARGET") -> KERJA | J6: =IF(COUNTIF($F6:I6,"KERJA")<$E6,"KERJA","OFF TARGET") -> KERJA | K6: OFF | L6: =IF(COUNTIF($F6:K6,"KERJA")<$E6,"KERJA","OFF TARGET") -> KERJA | M6: LIBUR | N6: =IF(COUNTIF($F6:M6,"KERJA")<$E6,"KERJA","OFF TARGET") -> KERJA | O6: =IF(COUNTIF($F6:N6,"KERJA")<$E6,"KERJA","OFF TARGET") -> KERJA | P6: =IF(COUNTIF($F6:O6,"KERJA")<$E6,"KERJA","OFF TARGET") -> KERJA | Q6: =IF(COUNTIF($F6:P6,"KERJA")<$E6,"KERJA","OFF TARGET") -> KERJA | R6: OFF | S6: =IF(COUNTIF($F6:R6,"KERJA")<$E6,"KERJA","OFF TARGET") -> KERJA | T6: =C6+COUNTIF(F6:S6,"KERJA") -> 23 | U6: =D6-T6 -> 1 | V6: =IF(U6=0,"TARGET 24 HK TERCAPAI",IF(U6>0,"MASIH KURANG "&U6&" HK","LEBIH "&ABS(U6)&" HK")) -> MASIH KURANG 1 HK
A7: Banjarmasin | B7: Herlisa | C7: =COUNTIF('Daily Report & WIP'!AD4:AD20,1) -> 13 | D7: 24 | E7: =MAX(D7-C7,0) -> 11 | F7: =IF($E7>0,"KERJA","OFF TARGET") -> KERJA | G7: =IF(COUNTIF($F7:F7,"KERJA")<$E7,"KERJA","OFF TARGET") -> KERJA | H7: =IF(COUNTIF($F7:G7,"KERJA")<$E7,"KERJA","OFF TARGET") -> KERJA | I7: =IF(COUNTIF($F7:H7,"KERJA")<$E7,"KERJA","OFF TARGET") -> KERJA | J7: =IF(COUNTIF($F7:I7,"KERJA")<$E7,"KERJA","OFF TARGET") -> KERJA | K7: OFF | L7: =IF(COUNTIF($F7:K7,"KERJA")<$E7,"KERJA","OFF TARGET") -> KERJA | M7: LIBUR | N7: =IF(COUNTIF($F7:M7,"KERJA")<$E7,"KERJA","OFF TARGET") -> KERJA | O7: =IF(COUNTIF($F7:N7,"KERJA")<$E7,"KERJA","OFF TARGET") -> KERJA | P7: =IF(COUNTIF($F7:O7,"KERJA")<$E7,"KERJA","OFF TARGET") -> KERJA | Q7: =IF(COUNTIF($F7:P7,"KERJA")<$E7,"KERJA","OFF TARGET") -> KERJA | R7: OFF | S7: =IF(COUNTIF($F7:R7,"KERJA")<$E7,"KERJA","OFF TARGET") -> KERJA | T7: =C7+COUNTIF(F7:S7,"KERJA") -> 24 | U7: =D7-T7 -> 0 | V7: =IF(U7=0,"TARGET 24 HK TERCAPAI",IF(U7>0,"MASIH KURANG "&U7&" HK","LEBIH "&ABS(U7)&" HK")) -> TARGET 24 HK TERCAPAI
A8: Banjarmasin | B8: Nur | C8: =COUNTIF('Daily Report & WIP'!AI4:AI20,1) -> 2 | D8: 24 | E8: =MAX(D8-C8,0) -> 22 | F8: =IF($E8>0,"KERJA","OFF TARGET") -> KERJA | G8: =IF(COUNTIF($F8:F8,"KERJA")<$E8,"KERJA","OFF TARGET") -> KERJA | H8: =IF(COUNTIF($F8:G8,"KERJA")<$E8,"KERJA","OFF TARGET") -> KERJA | I8: =IF(COUNTIF($F8:H8,"KERJA")<$E8,"KERJA","OFF TARGET") -> KERJA | J8: =IF(COUNTIF($F8:I8,"KERJA")<$E8,"KERJA","OFF TARGET") -> KERJA | K8: OFF | L8: =IF(COUNTIF($F8:K8,"KERJA")<$E8,"KERJA","OFF TARGET") -> KERJA | M8: LIBUR | N8: =IF(COUNTIF($F8:M8,"KERJA")<$E8,"KERJA","OFF TARGET") -> KERJA | O8: =IF(COUNTIF($F8:N8,"KERJA")<$E8,"KERJA","OFF TARGET") -> KERJA | P8: =IF(COUNTIF($F8:O8,"KERJA")<$E8,"KERJA","OFF TARGET") -> KERJA | Q8: =IF(COUNTIF($F8:P8,"KERJA")<$E8,"KERJA","OFF TARGET") -> KERJA | R8: OFF | S8: =IF(COUNTIF($F8:R8,"KERJA")<$E8,"KERJA","OFF TARGET") -> KERJA | T8: =C8+COUNTIF(F8:S8,"KERJA") -> 13 | U8: =D8-T8 -> 11 | V8: =IF(U8=0,"TARGET 24 HK TERCAPAI",IF(U8>0,"MASIH KURANG "&U8&" HK","LEBIH "&ABS(U8)&" HK")) -> MASIH KURANG 11 HK
A9: Balikpapan | B9: Grace | C9: =COUNTIF('Daily Report & WIP'!AD40:AD56,1) -> 12 | D9: 24 | E9: =MAX(D9-C9,0) -> 12 | F9: =IF($E9>0,"KERJA","OFF TARGET") -> KERJA | G9: =IF(COUNTIF($F9:F9,"KERJA")<$E9,"KERJA","OFF TARGET") -> KERJA | H9: =IF(COUNTIF($F9:G9,"KERJA")<$E9,"KERJA","OFF TARGET") -> KERJA | I9: =IF(COUNTIF($F9:H9,"KERJA")<$E9,"KERJA","OFF TARGET") -> KERJA | J9: =IF(COUNTIF($F9:I9,"KERJA")<$E9,"KERJA","OFF TARGET") -> KERJA | K9: OFF | L9: =IF(COUNTIF($F9:K9,"KERJA")<$E9,"KERJA","OFF TARGET") -> KERJA | M9: LIBUR | N9: =IF(COUNTIF($F9:M9,"KERJA")<$E9,"KERJA","OFF TARGET") -> KERJA | O9: =IF(COUNTIF($F9:N9,"KERJA")<$E9,"KERJA","OFF TARGET") -> KERJA | P9: =IF(COUNTIF($F9:O9,"KERJA")<$E9,"KERJA","OFF TARGET") -> KERJA | Q9: =IF(COUNTIF($F9:P9,"KERJA")<$E9,"KERJA","OFF TARGET") -> KERJA | R9: OFF | S9: =IF(COUNTIF($F9:R9,"KERJA")<$E9,"KERJA","OFF TARGET") -> KERJA | T9: =C9+COUNTIF(F9:S9,"KERJA") -> 23 | U9: =D9-T9 -> 1 | V9: =IF(U9=0,"TARGET 24 HK TERCAPAI",IF(U9>0,"MASIH KURANG "&U9&" HK","LEBIH "&ABS(U9)&" HK")) -> MASIH KURANG 1 HK
A10: Balikpapan | B10: Rami | C10: =COUNTIF('Daily Report & WIP'!AI40:AI56,1) -> 13 | D10: 24 | E10: =MAX(D10-C10,0) -> 11 | F10: =IF($E10>0,"KERJA","OFF TARGET") -> KERJA | G10: =IF(COUNTIF($F10:F10,"KERJA")<$E10,"KERJA","OFF TARGET") -> KERJA | H10: =IF(COUNTIF($F10:G10,"KERJA")<$E10,"KERJA","OFF TARGET") -> KERJA | I10: =IF(COUNTIF($F10:H10,"KERJA")<$E10,"KERJA","OFF TARGET") -> KERJA | J10: =IF(COUNTIF($F10:I10,"KERJA")<$E10,"KERJA","OFF TARGET") -> KERJA | K10: OFF | L10: =IF(COUNTIF($F10:K10,"KERJA")<$E10,"KERJA","OFF TARGET") -> KERJA | M10: LIBUR | N10: =IF(COUNTIF($F10:M10,"KERJA")<$E10,"KERJA","OFF TARGET") -> KERJA | O10: =IF(COUNTIF($F10:N10,"KERJA")<$E10,"KERJA","OFF TARGET") -> KERJA | P10: =IF(COUNTIF($F10:O10,"KERJA")<$E10,"KERJA","OFF TARGET") -> KERJA | Q10: =IF(COUNTIF($F10:P10,"KERJA")<$E10,"KERJA","OFF TARGET") -> KERJA | R10: OFF | S10: =IF(COUNTIF($F10:R10,"KERJA")<$E10,"KERJA","OFF TARGET") -> KERJA | T10: =C10+COUNTIF(F10:S10,"KERJA") -> 24 | U10: =D10-T10 -> 0 | V10: =IF(U10=0,"TARGET 24 HK TERCAPAI",IF(U10>0,"MASIH KURANG "&U10&" HK","LEBIH "&ABS(U10)&" HK")) -> TARGET 24 HK TERCAPAI
A11: Palangkaraya | B11: Fani Febriani | C11: =COUNTIF('Daily Report & WIP'!T83:T99,1) -> 14 | D11: 24 | E11: =MAX(D11-C11,0) -> 10 | F11: =IF($E11>0,"KERJA","OFF TARGET") -> KERJA | G11: =IF(COUNTIF($F11:F11,"KERJA")<$E11,"KERJA","OFF TARGET") -> KERJA | H11: =IF(COUNTIF($F11:G11,"KERJA")<$E11,"KERJA","OFF TARGET") -> KERJA | I11: =IF(COUNTIF($F11:H11,"KERJA")<$E11,"KERJA","OFF TARGET") -> KERJA | J11: =IF(COUNTIF($F11:I11,"KERJA")<$E11,"KERJA","OFF TARGET") -> KERJA | K11: =IF(COUNTIF($F11:J11,"KERJA")<$E11,"KERJA","OFF TARGET") -> KERJA | L11: OFF | M11: LIBUR | N11: =IF(COUNTIF($F11:M11,"KERJA")<$E11,"KERJA","OFF TARGET") -> KERJA | O11: =IF(COUNTIF($F11:N11,"KERJA")<$E11,"KERJA","OFF TARGET") -> KERJA | P11: =IF(COUNTIF($F11:O11,"KERJA")<$E11,"KERJA","OFF TARGET") -> KERJA | Q11: =IF(COUNTIF($F11:P11,"KERJA")<$E11,"KERJA","OFF TARGET") -> KERJA | R11: =IF(COUNTIF($F11:Q11,"KERJA")<$E11,"KERJA","OFF TARGET") -> OFF TARGET | S11: OFF | T11: =C11+COUNTIF(F11:S11,"KERJA") -> 24 | U11: =D11-T11 -> 0 | V11: =IF(U11=0,"TARGET 24 HK TERCAPAI",IF(U11>0,"MASIH KURANG "&U11&" HK","LEBIH "&ABS(U11)&" HK")) -> TARGET 24 HK TERCAPAI
A12: Palangkaraya | B12: Siska | C12: =COUNTIF('Daily Report & WIP'!Y83:Y99,1) -> 14 | D12: 24 | E12: =MAX(D12-C12,0) -> 10 | F12: =IF($E12>0,"KERJA","OFF TARGET") -> KERJA | G12: =IF(COUNTIF($F12:F12,"KERJA")<$E12,"KERJA","OFF TARGET") -> KERJA | H12: OFF | I12: =IF(COUNTIF($F12:H12,"KERJA")<$E12,"KERJA","OFF TARGET") -> KERJA | J12: =IF(COUNTIF($F12:I12,"KERJA")<$E12,"KERJA","OFF TARGET") -> KERJA | K12: =IF(COUNTIF($F12:J12,"KERJA")<$E12,"KERJA","OFF TARGET") -> KERJA | L12: =IF(COUNTIF($F12:K12,"KERJA")<$E12,"KERJA","OFF TARGET") -> KERJA | M12: LIBUR | N12: =IF(COUNTIF($F12:M12,"KERJA")<$E12,"KERJA","OFF TARGET") -> KERJA | O12: OFF | P12: =IF(COUNTIF($F12:O12,"KERJA")<$E12,"KERJA","OFF TARGET") -> KERJA | Q12: =IF(COUNTIF($F12:P12,"KERJA")<$E12,"KERJA","OFF TARGET") -> KERJA | R12: =IF(COUNTIF($F12:Q12,"KERJA")<$E12,"KERJA","OFF TARGET") -> KERJA | S12: =IF(COUNTIF($F12:R12,"KERJA")<$E12,"KERJA","OFF TARGET") -> OFF TARGET | T12: =C12+COUNTIF(F12:S12,"KERJA") -> 24 | U12: =D12-T12 -> 0 | V12: =IF(U12=0,"TARGET 24 HK TERCAPAI",IF(U12>0,"MASIH KURANG "&U12&" HK","LEBIH "&ABS(U12)&" HK")) -> TARGET 24 HK TERCAPAI
A13: Samarinda | B13: Fitriani | C13: =COUNTIF('Daily Report & WIP'!T40:T56,1) -> 12 | D13: 24 | E13: =MAX(D13-C13,0) -> 12 | F13: =IF($E13>0,"KERJA","OFF TARGET") -> KERJA | G13: =IF(COUNTIF($F13:F13,"KERJA")<$E13,"KERJA","OFF TARGET") -> KERJA | H13: =IF(COUNTIF($F13:G13,"KERJA")<$E13,"KERJA","OFF TARGET") -> KERJA | I13: =IF(COUNTIF($F13:H13,"KERJA")<$E13,"KERJA","OFF TARGET") -> KERJA | J13: =IF(COUNTIF($F13:I13,"KERJA")<$E13,"KERJA","OFF TARGET") -> KERJA | K13: OFF | L13: =IF(COUNTIF($F13:K13,"KERJA")<$E13,"KERJA","OFF TARGET") -> KERJA | M13: LIBUR | N13: =IF(COUNTIF($F13:M13,"KERJA")<$E13,"KERJA","OFF TARGET") -> KERJA | O13: =IF(COUNTIF($F13:N13,"KERJA")<$E13,"KERJA","OFF TARGET") -> KERJA | P13: =IF(COUNTIF($F13:O13,"KERJA")<$E13,"KERJA","OFF TARGET") -> KERJA | Q13: =IF(COUNTIF($F13:P13,"KERJA")<$E13,"KERJA","OFF TARGET") -> KERJA | R13: OFF | S13: =IF(COUNTIF($F13:R13,"KERJA")<$E13,"KERJA","OFF TARGET") -> KERJA | T13: =C13+COUNTIF(F13:S13,"KERJA") -> 23 | U13: =D13-T13 -> 1 | V13: =IF(U13=0,"TARGET 24 HK TERCAPAI",IF(U13>0,"MASIH KURANG "&U13&" HK","LEBIH "&ABS(U13)&" HK")) -> MASIH KURANG 1 HK
A14: Samarinda | B14: Desi Susanti | C14: =COUNTIF('Daily Report & WIP'!Y40:Y56,1) -> 13 | D14: 24 | E14: =MAX(D14-C14,0) -> 11 | F14: =IF($E14>0,"KERJA","OFF TARGET") -> KERJA | G14: =IF(COUNTIF($F14:F14,"KERJA")<$E14,"KERJA","OFF TARGET") -> KERJA | H14: =IF(COUNTIF($F14:G14,"KERJA")<$E14,"KERJA","OFF TARGET") -> KERJA | I14: =IF(COUNTIF($F14:H14,"KERJA")<$E14,"KERJA","OFF TARGET") -> KERJA | J14: =IF(COUNTIF($F14:I14,"KERJA")<$E14,"KERJA","OFF TARGET") -> KERJA | K14: OFF | L14: =IF(COUNTIF($F14:K14,"KERJA")<$E14,"KERJA","OFF TARGET") -> KERJA | M14: LIBUR | N14: =IF(COUNTIF($F14:M14,"KERJA")<$E14,"KERJA","OFF TARGET") -> KERJA | O14: =IF(COUNTIF($F14:N14,"KERJA")<$E14,"KERJA","OFF TARGET") -> KERJA | P14: =IF(COUNTIF($F14:O14,"KERJA")<$E14,"KERJA","OFF TARGET") -> KERJA | Q14: =IF(COUNTIF($F14:P14,"KERJA")<$E14,"KERJA","OFF TARGET") -> KERJA | R14: OFF | S14: =IF(COUNTIF($F14:R14,"KERJA")<$E14,"KERJA","OFF TARGET") -> KERJA | T14: =C14+COUNTIF(F14:S14,"KERJA") -> 24 | U14: =D14-T14 -> 0 | V14: =IF(U14=0,"TARGET 24 HK TERCAPAI",IF(U14>0,"MASIH KURANG "&U14&" HK","LEBIH "&ABS(U14)&" HK")) -> TARGET 24 HK TERCAPAI
A15: Makassar | B15: Amelia | C15: =COUNTIF('Daily Report & WIP'!T119:T135,1) -> 14 | D15: 24 | E15: =MAX(D15-C15,0) -> 10 | F15: =IF($E15>0,"KERJA","OFF TARGET") -> KERJA | G15: =IF(COUNTIF($F15:F15,"KERJA")<$E15,"KERJA","OFF TARGET") -> KERJA | H15: =IF(COUNTIF($F15:G15,"KERJA")<$E15,"KERJA","OFF TARGET") -> KERJA | I15: =IF(COUNTIF($F15:H15,"KERJA")<$E15,"KERJA","OFF TARGET") -> KERJA | J15: =IF(COUNTIF($F15:I15,"KERJA")<$E15,"KERJA","OFF TARGET") -> KERJA | K15: OFF | L15: =IF(COUNTIF($F15:K15,"KERJA")<$E15,"KERJA","OFF TARGET") -> KERJA | M15: LIBUR | N15: =IF(COUNTIF($F15:M15,"KERJA")<$E15,"KERJA","OFF TARGET") -> KERJA | O15: =IF(COUNTIF($F15:N15,"KERJA")<$E15,"KERJA","OFF TARGET") -> KERJA | P15: =IF(COUNTIF($F15:O15,"KERJA")<$E15,"KERJA","OFF TARGET") -> KERJA | Q15: =IF(COUNTIF($F15:P15,"KERJA")<$E15,"KERJA","OFF TARGET") -> KERJA | R15: OFF | S15: =IF(COUNTIF($F15:R15,"KERJA")<$E15,"KERJA","OFF TARGET") -> OFF TARGET | T15: =C15+COUNTIF(F15:S15,"KERJA") -> 24 | U15: =D15-T15 -> 0 | V15: =IF(U15=0,"TARGET 24 HK TERCAPAI",IF(U15>0,"MASIH KURANG "&U15&" HK","LEBIH "&ABS(U15)&" HK")) -> TARGET 24 HK TERCAPAI
A16: Makassar | B16: Dira/Nadira | C16: =COUNTIF('Daily Report & WIP'!Y119:Y135,1) -> 11 | D16: 24 | E16: =MAX(D16-C16,0) -> 13 | F16: =IF($E16>0,"KERJA","OFF TARGET") -> KERJA | G16: =IF(COUNTIF($F16:F16,"KERJA")<$E16,"KERJA","OFF TARGET") -> KERJA | H16: =IF(COUNTIF($F16:G16,"KERJA")<$E16,"KERJA","OFF TARGET") -> KERJA | I16: =IF(COUNTIF($F16:H16,"KERJA")<$E16,"KERJA","OFF TARGET") -> KERJA | J16: =IF(COUNTIF($F16:I16,"KERJA")<$E16,"KERJA","OFF TARGET") -> KERJA | K16: OFF | L16: =IF(COUNTIF($F16:K16,"KERJA")<$E16,"KERJA","OFF TARGET") -> KERJA | M16: LIBUR | N16: =IF(COUNTIF($F16:M16,"KERJA")<$E16,"KERJA","OFF TARGET") -> KERJA | O16: =IF(COUNTIF($F16:N16,"KERJA")<$E16,"KERJA","OFF TARGET") -> KERJA | P16: =IF(COUNTIF($F16:O16,"KERJA")<$E16,"KERJA","OFF TARGET") -> KERJA | Q16: =IF(COUNTIF($F16:P16,"KERJA")<$E16,"KERJA","OFF TARGET") -> KERJA | R16: OFF | S16: =IF(COUNTIF($F16:R16,"KERJA")<$E16,"KERJA","OFF TARGET") -> KERJA | T16: =C16+COUNTIF(F16:S16,"KERJA") -> 22 | U16: =D16-T16 -> 2 | V16: =IF(U16=0,"TARGET 24 HK TERCAPAI",IF(U16>0,"MASIH KURANG "&U16&" HK","LEBIH "&ABS(U16)&" HK")) -> MASIH KURANG 2 HK
A17: Makassar | B17: Nurhijrah | C17: =COUNTIF('Daily Report & WIP'!AD119:AD135,1) -> 13 | D17: 24 | E17: =MAX(D17-C17,0) -> 11 | F17: =IF($E17>0,"KERJA","OFF TARGET") -> KERJA | G17: =IF(COUNTIF($F17:F17,"KERJA")<$E17,"KERJA","OFF TARGET") -> KERJA | H17: =IF(COUNTIF($F17:G17,"KERJA")<$E17,"KERJA","OFF TARGET") -> KERJA | I17: =IF(COUNTIF($F17:H17,"KERJA")<$E17,"KERJA","OFF TARGET") -> KERJA | J17: =IF(COUNTIF($F17:I17,"KERJA")<$E17,"KERJA","OFF TARGET") -> KERJA | K17: OFF | L17: =IF(COUNTIF($F17:K17,"KERJA")<$E17,"KERJA","OFF TARGET") -> KERJA | M17: LIBUR | N17: =IF(COUNTIF($F17:M17,"KERJA")<$E17,"KERJA","OFF TARGET") -> KERJA | O17: =IF(COUNTIF($F17:N17,"KERJA")<$E17,"KERJA","OFF TARGET") -> KERJA | P17: =IF(COUNTIF($F17:O17,"KERJA")<$E17,"KERJA","OFF TARGET") -> KERJA | Q17: =IF(COUNTIF($F17:P17,"KERJA")<$E17,"KERJA","OFF TARGET") -> KERJA | R17: OFF | S17: =IF(COUNTIF($F17:R17,"KERJA")<$E17,"KERJA","OFF TARGET") -> KERJA | T17: =C17+COUNTIF(F17:S17,"KERJA") -> 24 | U17: =D17-T17 -> 0 | V17: =IF(U17=0,"TARGET 24 HK TERCAPAI",IF(U17>0,"MASIH KURANG "&U17&" HK","LEBIH "&ABS(U17)&" HK")) -> TARGET 24 HK TERCAPAI
A18: Manado | B18: Dea | C18: =COUNTIF('Daily Report & WIP'!AD83:AD99,1) -> 12 | D18: 24 | E18: =MAX(D18-C18,0) -> 12 | F18: =IF($E18>0,"KERJA","OFF TARGET") -> KERJA | G18: =IF(COUNTIF($F18:F18,"KERJA")<$E18,"KERJA","OFF TARGET") -> KERJA | H18: =IF(COUNTIF($F18:G18,"KERJA")<$E18,"KERJA","OFF TARGET") -> KERJA | I18: =IF(COUNTIF($F18:H18,"KERJA")<$E18,"KERJA","OFF TARGET") -> KERJA | J18: =IF(COUNTIF($F18:I18,"KERJA")<$E18,"KERJA","OFF TARGET") -> KERJA | K18: OFF | L18: =IF(COUNTIF($F18:K18,"KERJA")<$E18,"KERJA","OFF TARGET") -> KERJA | M18: LIBUR | N18: =IF(COUNTIF($F18:M18,"KERJA")<$E18,"KERJA","OFF TARGET") -> KERJA | O18: =IF(COUNTIF($F18:N18,"KERJA")<$E18,"KERJA","OFF TARGET") -> KERJA | P18: =IF(COUNTIF($F18:O18,"KERJA")<$E18,"KERJA","OFF TARGET") -> KERJA | Q18: =IF(COUNTIF($F18:P18,"KERJA")<$E18,"KERJA","OFF TARGET") -> KERJA | R18: OFF | S18: =IF(COUNTIF($F18:R18,"KERJA")<$E18,"KERJA","OFF TARGET") -> KERJA | T18: =C18+COUNTIF(F18:S18,"KERJA") -> 23 | U18: =D18-T18 -> 1 | V18: =IF(U18=0,"TARGET 24 HK TERCAPAI",IF(U18>0,"MASIH KURANG "&U18&" HK","LEBIH "&ABS(U18)&" HK")) -> MASIH KURANG 1 HK
A19: Manado | B19: Regina | C19: =COUNTIF('Daily Report & WIP'!AI83:AI99,1) -> 13 | D19: 24 | E19: =MAX(D19-C19,0) -> 11 | F19: =IF($E19>0,"KERJA","OFF TARGET") -> KERJA | G19: =IF(COUNTIF($F19:F19,"KERJA")<$E19,"KERJA","OFF TARGET") -> KERJA | H19: =IF(COUNTIF($F19:G19,"KERJA")<$E19,"KERJA","OFF TARGET") -> KERJA | I19: =IF(COUNTIF($F19:H19,"KERJA")<$E19,"KERJA","OFF TARGET") -> KERJA | J19: =IF(COUNTIF($F19:I19,"KERJA")<$E19,"KERJA","OFF TARGET") -> KERJA | K19: OFF | L19: =IF(COUNTIF($F19:K19,"KERJA")<$E19,"KERJA","OFF TARGET") -> KERJA | M19: LIBUR | N19: =IF(COUNTIF($F19:M19,"KERJA")<$E19,"KERJA","OFF TARGET") -> KERJA | O19: =IF(COUNTIF($F19:N19,"KERJA")<$E19,"KERJA","OFF TARGET") -> KERJA | P19: =IF(COUNTIF($F19:O19,"KERJA")<$E19,"KERJA","OFF TARGET") -> KERJA | Q19: =IF(COUNTIF($F19:P19,"KERJA")<$E19,"KERJA","OFF TARGET") -> KERJA | R19: OFF | S19: =IF(COUNTIF($F19:R19,"KERJA")<$E19,"KERJA","OFF TARGET") -> KERJA | T19: =C19+COUNTIF(F19:S19,"KERJA") -> 24 | U19: =D19-T19 -> 0 | V19: =IF(U19=0,"TARGET 24 HK TERCAPAI",IF(U19>0,"MASIH KURANG "&U19&" HK","LEBIH "&ABS(U19)&" HK")) -> TARGET 24 HK TERCAPAI

Sheet ZONA SPG
A1: ZONA SPG AGUSTUS 2026 - UPDATE 1-17 AGUSTUS
A3: AREA | B3: SPG | C3: HK ACTUAL | D3: TARGET HK | E3: ACHIEVEMENT | F3: RATIO | G3: KOMITMEN RATIO | H3: GAP KARTON/HARI | I3: ZONA | J3: STATUS TARGET
A4: Banjarmasin | B4: Nurul | C4: ='Daily Report & WIP'!AP6 -> 12 | D4: ='Daily Report & WIP'!AO6 -> 24 | E4: ='Daily Report & WIP'!BB6 -> 0.25185185 | F4: ='Daily Report & WIP'!BE6 -> 0.41607843 | G4: ='Daily Report & WIP'!BM6 -> 0.27 | H4: ='Daily Report & WIP'!BH6 -> 8.4166667 | I4: =IF(OR(F4>G4+5%,H4>8),"MERAH",IF(OR(F4>G4,H4>5),"KUNING","HIJAU")) -> MERAH | J4: =IF(E4>=1,"TERCAPAI","KEJAR TARGET") -> KEJAR TARGET
A5: Banjarmasin | B5: Khoirunisa | C5: ='Daily Report & WIP'!AP7 -> 12 | D5: ='Daily Report & WIP'!AO7 -> 24 | E5: ='Daily Report & WIP'!BB7 -> 0.47407407 | F5: ='Daily Report & WIP'!BE7 -> 0.2215224 | G5: ='Daily Report & WIP'!BM7 -> 0.27 | H5: ='Daily Report & WIP'!BH7 -> 5.9166667 | I5: =IF(OR(F5>G5+5%,H5>8),"MERAH",IF(OR(F5>G5,H5>5),"KUNING","HIJAU")) -> KUNING | J5: =IF(E5>=1,"TERCAPAI","KEJAR TARGET") -> KEJAR TARGET
A6: Banjarmasin | B6: Herlisa | C6: ='Daily Report & WIP'!AP8 -> 13 | D6: ='Daily Report & WIP'!AO8 -> 24 | E6: ='Daily Report & WIP'!BB8 -> 0.39259259 | F6: ='Daily Report & WIP'!BE8 -> 0.28916143 | G6: ='Daily Report & WIP'!BM8 -> 0.27 | H6: ='Daily Report & WIP'!BH8 -> 7.4545455 | I6: =IF(OR(F6>G6+5%,H6>8),"MERAH",IF(OR(F6>G6,H6>5),"KUNING","HIJAU")) -> KUNING | J6: =IF(E6>=1,"TERCAPAI","KEJAR TARGET") -> KEJAR TARGET
A7: Banjarmasin | B7: Nur | C7: ='Daily Report & WIP'!AP9 -> 2 | D7: ='Daily Report & WIP'!AO9 -> 24 | E7: ='Daily Report & WIP'!BB9 -> 0.12222222 | F7: ='Daily Report & WIP'!BE9 -> 0.14146667 | G7: ='Daily Report & WIP'!BM9 -> 0.27 | H7: ='Daily Report & WIP'!BH9 -> 5.3863636 | I7: =IF(OR(F7>G7+5%,H7>8),"MERAH",IF(OR(F7>G7,H7>5),"KUNING","HIJAU")) -> KUNING | J7: =IF(E7>=1,"TERCAPAI","KEJAR TARGET") -> KEJAR TARGET
A8: Balikpapan | B8: Grace | C8: ='Daily Report & WIP'!AP11 -> 13 | D8: ='Daily Report & WIP'!AO11 -> 24 | E8: ='Daily Report & WIP'!BB11 -> 0.14814815 | F8: ='Daily Report & WIP'!BE11 -> 0.76260468 | G8: ='Daily Report & WIP'!BM11 -> 0.3 | H8: ='Daily Report & WIP'!BH11 -> 10.454545 | I8: =IF(OR(F8>G8+5%,H8>8),"MERAH",IF(OR(F8>G8,H8>5),"KUNING","HIJAU")) -> MERAH | J8: =IF(E8>=1,"TERCAPAI","KEJAR TARGET") -> KEJAR TARGET
A9: Balikpapan | B9: Rami | C9: ='Daily Report & WIP'!AP12 -> 14 | D9: ='Daily Report & WIP'!AO12 -> 24 | E9: ='Daily Report & WIP'!BB12 -> 0.20740741 | F9: ='Daily Report & WIP'!BE12 -> 0.6013646 | G9: ='Daily Report & WIP'!BM12 -> 0.3 | H9: ='Daily Report & WIP'!BH12 -> 10.7 | I9: =IF(OR(F9>G9+5%,H9>8),"MERAH",IF(OR(F9>G9,H9>5),"KUNING","HIJAU")) -> MERAH | J9: =IF(E9>=1,"TERCAPAI","KEJAR TARGET") -> KEJAR TARGET
A10: Palangkaraya | B10: Fani Febriani | C10: ='Daily Report & WIP'!AP14 -> 14 | D10: ='Daily Report & WIP'!AO14 -> 24 | E10: ='Daily Report & WIP'!BB14 -> 0.28858025 | F10: ='Daily Report & WIP'!BE14 -> 0.42957936 | G10: ='Daily Report & WIP'!BM14 -> 0.27 | H10: ='Daily Report & WIP'!BH14 -> 9.6041667 | I10: =IF(OR(F10>G10+5%,H10>8),"MERAH",IF(OR(F10>G10,H10>5),"KUNING","HIJAU")) -> MERAH | J10: =IF(E10>=1,"TERCAPAI","KEJAR TARGET") -> KEJAR TARGET
A11: Palangkaraya | B11: Siska | C11: ='Daily Report & WIP'!AP15 -> 14 | D11: ='Daily Report & WIP'!AO15 -> 24 | E11: ='Daily Report & WIP'!BB15 -> 0.30740741 | F11: ='Daily Report & WIP'!BE15 -> 0.38587383 | G11: ='Daily Report & WIP'!BM15 -> 0.27 | H11: ='Daily Report & WIP'!BH15 -> 9.35 | I11: =IF(OR(F11>G11+5%,H11>8),"MERAH",IF(OR(F11>G11,H11>5),"KUNING","HIJAU")) -> MERAH | J11: =IF(E11>=1,"TERCAPAI","KEJAR TARGET") -> KEJAR TARGET
A12: Samarinda | B12: Fitriani | C12: ='Daily Report & WIP'!AP17 -> 13 | D12: ='Daily Report & WIP'!AO17 -> 24 | E12: ='Daily Report & WIP'!BB17 -> 0.26666667 | F12: ='Daily Report & WIP'!BE17 -> 0.4043588 | G12: ='Daily Report & WIP'!BM17 -> 0.3 | H12: ='Daily Report & WIP'!BH17 -> 9 | I12: =IF(OR(F12>G12+5%,H12>8),"MERAH",IF(OR(F12>G12,H12>5),"KUNING","HIJAU")) -> MERAH | J12: =IF(E12>=1,"TERCAPAI","KEJAR TARGET") -> KEJAR TARGET
B13: Desi Susanti | C13: ='Daily Report & WIP'!AP18 -> 14 | D13: ='Daily Report & WIP'!AO18 -> 24 | E13: ='Daily Report & WIP'!BB18 -> 0.25185185 | F13: ='Daily Report & WIP'!BE18 -> 0.47839632 | G13: ='Daily Report & WIP'!BM18 -> 0.3 | H13: ='Daily Report & WIP'!BH18 -> 10.1 | I13: =IF(OR(F13>G13+5%,H13>8),"MERAH",IF(OR(F13>G13,H13>5),"KUNING","HIJAU")) -> MERAH | J13: =IF(E13>=1,"TERCAPAI","KEJAR TARGET") -> KEJAR TARGET
A14: Makassar | B14: Amelia | C14: ='Daily Report & WIP'!AP20 -> 16 | D14: ='Daily Report & WIP'!AO20 -> 24 | E14: ='Daily Report & WIP'!BB20 -> 0.15030864 | F14: ='Daily Report & WIP'!BE20 -> 0.89081267 | G14: ='Daily Report & WIP'!BM20 -> 0.3 | H14: ='Daily Report & WIP'!BH20 -> 14.338542 | I14: =IF(OR(F14>G14+5%,H14>8),"MERAH",IF(OR(F14>G14,H14>5),"KUNING","HIJAU")) -> MERAH | J14: =IF(E14>=1,"TERCAPAI","KEJAR TARGET") -> KEJAR TARGET
A15: Makassar | B15: Dira/Nadira | C15: ='Daily Report & WIP'!AP21 -> 13 | D15: ='Daily Report & WIP'!AO21 -> 24 | E15: ='Daily Report & WIP'!BB21 -> 0.06882716 | F15: ='Daily Report & WIP'!BE21 -> 1.9184884 | G15: ='Daily Report & WIP'!BM21 -> 0.3 | H15: ='Daily Report & WIP'!BH21 -> 11.42803 | I15: =IF(OR(F15>G15+5%,H15>8),"MERAH",IF(OR(F15>G15,H15>5),"KUNING","HIJAU")) -> MERAH | J15: =IF(E15>=1,"TERCAPAI","KEJAR TARGET") -> KEJAR TARGET
A16: Makassar | B16: Nurhijrah | C16: ='Daily Report & WIP'!AP22 -> 15 | D16: ='Daily Report & WIP'!AO22 -> 24 | E16: ='Daily Report & WIP'!BB22 -> 0.14660494 | F16: ='Daily Report & WIP'!BE22 -> 0.88630888 | G16: ='Daily Report & WIP'!BM22 -> 0.3 | H16: ='Daily Report & WIP'!BH22 -> 12.800926 | I16: =IF(OR(F16>G16+5%,H16>8),"MERAH",IF(OR(F16>G16,H16>5),"KUNING","HIJAU")) -> MERAH | J16: =IF(E16>=1,"TERCAPAI","KEJAR TARGET") -> KEJAR TARGET
A17: Manado | B17: Dea | C17: ='Daily Report & WIP'!AP24 -> 13 | D17: ='Daily Report & WIP'!AO24 -> 24 | E17: ='Daily Report & WIP'!BB24 -> 0.11666667 | F17: ='Daily Report & WIP'!BE24 -> 0.97121986 | G17: ='Daily Report & WIP'!BM24 -> 0.3 | H17: ='Daily Report & WIP'!BH24 -> 10.840909 | I17: =IF(OR(F17>G17+5%,H17>8),"MERAH",IF(OR(F17>G17,H17>5),"KUNING","HIJAU")) -> MERAH | J17: =IF(E17>=1,"TERCAPAI","KEJAR TARGET") -> KEJAR TARGET
A18: Manado | B18: Regina | C18: ='Daily Report & WIP'!AP25 -> 13 | D18: ='Daily Report & WIP'!AO25 -> 24 | E18: ='Daily Report & WIP'!BB25 -> 0.1154321 | F18: ='Daily Report & WIP'!BE25 -> 0.97641355 | G18: ='Daily Report & WIP'!BM25 -> 0.3 | H18: ='Daily Report & WIP'!BH25 -> 10.856061 | I18: =IF(OR(F18>G18+5%,H18>8),"MERAH",IF(OR(F18>G18,H18>5),"KUNING","HIJAU")) -> MERAH | J18: =IF(E18>=1,"TERCAPAI","KEJAR TARGET") -> KEJAR TARGET

Sheet COACHING
A1: WEEK 2
A2: No | B2: Area | C2: Nama SPG | D2: Jumlah HK | E2: MTD | H2: AVG SELLING | I2: DAILY SELLING IN CAN
E4: SELLING IN CAN | F4: SAMPLING CUP | G4: DISPLAY RAK | I4: SEBELUM COACHING | M4: AVG PERDAY | N4: SEBELUM COACHING | R4: AVG PERDAY
I5: 46146 | J5: 46147 | K5: 46148 | L5: 46149 | N5: 46153 | O5: 46154 | P5: 46155 | Q5: 46156
A6: 1 | B6: BANJARMASIN | C6: Fatmawati | D6: 4 | E6: =SUM(I6:L6) -> 204 | F6: 8 | G6: 2 | H6: =E6/D6 -> 51 | I6: 48 | J6: 72 | K6: 36 | L6: 48 | M6: =AVERAGE(I6:L6) -> 51 | N6: 69 | O6: 37 | P6: 121 | Q6: 99 | R6: =AVERAGE(N6:Q6) -> 81.5
A7: 2 | C7: Khoirunisa | D7: 4 | E7: =SUM(I7:L7) -> 360 | F7: 100 | G7: 2 | H7: =E7/D7 -> 90 | I7: 72 | J7: 72 | K7: 72 | L7: 144 | M7: =AVERAGE(I7:L7) -> 90 | N7: 168 | O7: 96 | P7: 120 | Q7: 72 | R7: =AVERAGE(N7:Q7) -> 114

Sheet FEB VS MARET
Y1: SERI RAHMI (JOINT DATE 18 Januari 2026) | AD1: KHOIRUNISA (JOINT DATE 10 Januari 2026) | AI1: HERLISA (JOINT DATE 2 Desember 2025) | AN1: EMA (JOINT PER TANGGAL 2 MARET 2026) | AS1: FITRIANI (JOINT PER TANGGAL 7 FEBRUARI 2026) | AX1: DESI SUSANTI (JOINT PER TANGGAL 20 FEBRUARI 2026)
Y2: Tanggal | Z2: STATUS ABSENSI | AA2: Selling (pcs) | AB2: Value (Rp) | AD2: Tanggal | AE2: STATUS ABSENSI | AF2: Selling (pcs) | AG2: Value (Rp) | AI2: Tanggal | AJ2: STATUS ABSENSI | AK2: Selling (pcs) | AL2: Value (Rp) | AN2: Tanggal | AO2: STATUS ABSENSI | AP2: Selling (pcs) | AQ2: Value (Rp) | AS2: Tanggal | AT2: STATUS ABSENSI | AU2: Selling (pcs) | AV2: Value (Rp) | AX2: Tanggal | AY2: STATUS ABSENSI | AZ2: Selling (pcs) | BA2: Value (Rp)
Y3: 46082 | Z3: OFF | AD3: 46082 | AE3: OFF | AI3: 46082 | AJ3: OFF DAY | AN3: 46082 | AO3: OFF DAY | AS3: 46082 | AT3: OFF DAY | AX3: 46082 | AY3: OFF DAY
Y4: 46083 | Z4: 1 | AA4: 96 | AB4: 480000 | AD4: 46083 | AE4: 1 | AF4: 72 | AG4: 360000 | AI4: 46083 | AJ4: 1 | AK4: 72 | AL4: 360000 | AN4: 46083 | AO4: 1 | AP4: 72 | AQ4: 354000 | AS4: 46083 | AT4: 1 | AU4: 24 | AV4: 132000 | AX4: 46083 | AY4: 1 | AZ4: 48 | BA4: 264000
Y5: 46084 | Z5: 1 | AA5: 72 | AB5: 360000 | AD5: 46084 | AE5: 1 | AF5: 48 | AG5: 240000 | AI5: 46084 | AJ5: 1 | AK5: 72 | AL5: 360000 | AN5: 46084 | AO5: 1 | AP5: 96 | AQ5: 462000 | AS5: 46084 | AT5: 1 | AU5: 96 | AV5: 528000 | AX5: 46084 | AY5: 1 | AZ5: 24 | BA5: 132000
Y6: 46085 | Z6: OFF TUKAR MINGGU | AD6: 46085 | AE6: 1 | AF6: 48 | AG6: 240000 | AI6: 46085 | AJ6: 1 | AK6: 72 | AL6: 360000 | AN6: 46085 | AO6: 1 | AP6: 96 | AQ6: 474000 | AS6: 46085 | AT6: 1 | AU6: 96 | AV6: 528000 | AX6: 46085 | AY6: 1 | AZ6: 48 | BA6: 264000
Y7: 46086 | Z7: 1 | AA7: 72 | AB7: 360000 | AD7: 46086 | AE7: 1 | AF7: 72 | AG7: 360000 | AI7: 46086 | AJ7: 1 | AK7: 48 | AL7: 240000 | AN7: 46086 | AO7: 1 | AP7: 240 | AQ7: 1152000 | AS7: 46086 | AT7: 1 | AU7: 72 | AV7: 369000 | AX7: 46086 | AY7: 1 | AZ7: 72 | BA7: 369000
Y8: 46087 | Z8: 1 | AA8: 72 | AB8: 360000 | AD8: 46087 | AE8: 1 | AF8: 72 | AG8: 360000 | AI8: 46087 | AJ8: 1 | AK8: 96 | AL8: 480000 | AN8: 46087 | AO8: 1 | AP8: 96 | AQ8: 480000 | AS8: 46087 | AT8: IZIN | AX8: 46087 | AY8: 1 | AZ8: 72 | BA8: 369000
Y9: 46088 | Z9: 1 | AA9: 120 | AB9: 575000 | AD9: 46088 | AE9: 1 | AF9: 96 | AG9: 480000 | AI9: 46088 | AJ9: 1 | AK9: 96 | AL9: 480000 | AN9: 46088 | AO9: 1 | AP9: 53 | AQ9: 259000 | AS9: 46088 | AT9: 1 | AU9: 72 | AV9: 369000 | AX9: 46088 | AY9: 1 | AZ9: 72 | BA9: 369000
Y10: 46089 | Z10: 1 | AA10: 48 | AB10: 240000 | AD10: 46089 | AE10: 1 | AF10: 72 | AG10: 360000 | AI10: 46089 | AJ10: 1 | AK10: 168 | AL10: 840000 | AN10: 46089 | AO10: OFF DAY | AS10: 46089 | AT10: 1 | AU10: 96 | AV10: 528000 | AX10: 46089 | AY10: OFF DAY
Y11: 46090 | Z11: 1 | AA11: 96 | AB11: 480000 | AD11: 46090 | AE11: 1 | AF11: 72 | AG11: 360000 | AI11: 46090 | AJ11: 1 | AK11: 96 | AL11: 480000 | AN11: 46090 | AO11: 1 | AP11: 40 | AQ11: 200000 | AS11: 46090 | AT11: 1 | AU11: 72 | AV11: 369000 | AX11: 46090 | AY11: 1 | AZ11: 96 | BA11: 528000
Y12: 46091 | Z12: 1 | AA12: 72 | AB12: 360000 | AD12: 46091 | AE12: 1 | AF12: 48 | AG12: 240000 | AI12: 46091 | AJ12: 1 | AK12: 72 | AL12: 360000 | AN12: 46091 | AO12: 1 | AP12: 42 | AQ12: 210000 | AS12: 46091 | AT12: 1 | AU12: 96 | AV12: 528000 | AX12: 46091 | AY12: 1 | AZ12: 144 | BA12: 792000
Y13: 46092 | Z13: 1 | AA13: 48 | AB13: 240000 | AD13: 46092 | AE13: 1 | AF13: 144 | AG13: 720000 | AI13: 46092 | AJ13: 1 | AK13: 48 | AL13: 260000 | AN13: 46092 | AO13: 1 | AP13: 48 | AQ13: 228000 | AS13: 46092 | AT13: 1 | AU13: 72 | AV13: 396000 | AX13: 46092 | AY13: 1 | AZ13: 24 | BA13: 132000
Y14: 46093 | Z14: 1 | AA14: 48 | AB14: 240000 | AD14: 46093 | AE14: 1 | AF14: 96 | AG14: 480000 | AI14: 46093 | AJ14: 1 | AK14: 48 | AL14: 260000 | AN14: 46093 | AO14: 1 | AP14: 23 | AQ14: 115000 | AS14: 46093 | AT14: 1 | AU14: 96 | AV14: 528000 | AX14: 46093 | AY14: 1 | AZ14: 96 | BA14: 528000
Y15: 46094 | AD15: 46094 | AI15: 46094 | AN15: 46094 | AS15: 46094 | AX15: 46094
Y16: 46095 | AD16: 46095 | AI16: 46095 | AN16: 46095 | AS16: 46095 | AX16: 46095
Y17: 46096 | AA17: 0 | AD17: 46096 | AF17: 0 | AI17: 46096 | AK17: 0 | AN17: 46096 | AP17: 0 | AS17: 46096 | AU17: 0 | AX17: 46096 | AZ17: 0
Y18: 46097 | AD18: 46097 | AI18: 46097 | AN18: 46097 | AS18: 46097 | AX18: 46097
Y19: 46098 | AD19: 46098 | AI19: 46098 | AN19: 46098 | AS19: 46098 | AX19: 46098
Y20: 46099 | AD20: 46099 | AI20: 46099 | AN20: 46099 | AS20: 46099 | AX20: 46099
Y21: 46100 | AD21: 46100 | AI21: 46100 | AN21: 46100 | AS21: 46100 | AX21: 46100
Y22: 46101 | AD22: 46101 | AI22: 46101 | AN22: 46101 | AS22: 46101 | AX22: 46101
Y23: 46102 | AD23: 46102 | AI23: 46102 | AN23: 46102 | AS23: 46102 | AX23: 46102
Y24: 46103 | AA24: 0 | AD24: 46103 | AF24: 0 | AI24: 46103 | AK24: 0 | AN24: 46103 | AP24: 0 | AS24: 46103 | AU24: 0 | AX24: 46103 | AZ24: 0
Y25: 46104 | AD25: 46104 | AI25: 46104 | AN25: 46104 | AS25: 46104 | AX25: 46104
Y26: 46105 | AD26: 46105 | AI26: 46105 | AN26: 46105 | AS26: 46105 | AX26: 46105
Y27: 46106 | AD27: 46106 | AI27: 46106 | AN27: 46106 | AS27: 46106 | AX27: 46106
Y28: 46107 | AD28: 46107 | AI28: 46107 | AN28: 46107 | AS28: 46107 | AX28: 46107
Y29: 46108 | AD29: 46108 | AI29: 46108 | AN29: 46108 | AS29: 46108 | AX29: 46108
Y30: 46109 | AD30: 46109 | AI30: 46109 | AN30: 46109 | AS30: 46109 | AX30: 46109
Y31: 46110 | AD31: 46110 | AI31: 46110 | AN31: 46110 | AS31: 46110 | AX31: 46110
Y32: 46111 | AD32: 46111 | AI32: 46111 | AN32: 46111 | AS32: 46111 | AX32: 46111
Y33: 46112 | AD33: 46112 | AI33: 46112 | AN33: 46112 | AS33: 46112 | AX33: 46112
Y38: ARNITA (JOINT PER TANGGAL 26 JANUARI 2026) | AD38: FANI FEBRIANI (JOINT PER TANGGAL 27 DESEMBER 2025) | AI38: EMILIA (JOINT PER TANGGAL 4 MARET 2026) | AN38: WINDA (JOINT PER TANGGAL 4 DESEMBER 2025) | AS38: NOR HASANAH (JOINT PER TANGGAL 5 MARET 2026)
Y39: Tanggal | Z39: STATUS ABSENSI | AA39: Selling (pcs) | AB39: Value (Rp) | AD39: Tanggal | AE39: STATUS ABSENSI | AF39: Selling (pcs) | AG39: Value (Rp) | AI39: Tanggal | AJ39: STATUS ABSENSI | AK39: Selling (pcs) | AL39: Value (Rp) | AN39: Tanggal | AO39: STATUS ABSENSI | AP39: Selling (pcs) | AQ39: Value (Rp) | AS39: Tanggal | AT39: STATUS ABSENSI | AU39: Selling (pcs) | AV39: Value (Rp)
Y40: 46082 | Z40: OFF DAY | AD40: 46082 | AE40: 1 | AF40: 24 | AG40: 127000 | AI40: 46082 | AN40: 46082 | AO40: OFF DAY | AS40: 46082
Y41: 46083 | Z41: 1 | AA41: 102 | AB41: 566000 | AD41: 46083 | AE41: OFF DAY | AI41: 46083 | AN41: 46083 | AO41: 1 | AP41: 38 | AQ41: 209000 | AS41: 46083
Y42: 46084 | Z42: 1 | AA42: 96 | AB42: 532000 | AD42: 46084 | AE42: 1 | AF42: 48 | AG42: 252000 | AI42: 46084 | AN42: 46084 | AO42: 1 | AP42: 96 | AQ42: 528000 | AS42: 46084
Y43: 46085 | Z43: 1 | AA43: 96 | AB43: 532000 | AD43: 46085 | AE43: 1 | AF43: 96 | AG43: 508000 | AI43: 46085 | AJ43: 1 | AK43: 48 | AL43: 264000 | AN43: 46085 | AO43: SAKIT | AS43: 46085
Y44: 46086 | Z44: 1 | AA44: 126 | AB44: 726000 | AD44: 46086 | AE44: 1 | AF44: 24 | AG44: 126000 | AI44: 46086 | AJ44: OFF DAY | AN44: 46086 | AO44: 1 | AP44: 51 | AQ44: 280500 | AS44: 46086 | AT44: 1 | AU44: 24 | AV44: 125000
Y45: 46087 | Z45: 1 | AA45: 96 | AB45: 524000 | AD45: 46087 | AE45: 1 | AF45: 96 | AG45: 516000 | AI45: 46087 | AJ45: 1 | AK45: 24 | AL45: 132000 | AN45: 46087 | AO45: 1 | AP45: 55 | AQ45: 302500 | AS45: 46087 | AT45: 1 | AU45: 24 | AV45: 125000
Y46: 46088 | Z46: 1 | AA46: 101 | AB46: 582000 | AD46: 46088 | AE46: 1 | AF46: 480 | AG46: 2520000 | AI46: 46088 | AJ46: 1 | AK46: 24 | AL46: 132000 | AN46: 46088 | AO46: 1 | AP46: 48 | AQ46: 264000 | AS46: 46088 | AT46: 1 | AU46: 48 | AV46: 250000
Y47: 46089 | Z47: 1 | AA47: 96 | AB47: 552000 | AD47: 46089 | AE47: 1 | AF47: 24 | AG47: 127000 | AI47: 46089 | AJ47: 1 | AK47: 96 | AL47: 520000 | AN47: 46089 | AO47: 1 | AP47: 96 | AQ47: 528000 | AS47: 46089 | AT47: 1 | AU47: 48 | AV47: 250000
Y48: 46090 | Z48: 1 | AA48: 96 | AB48: 524000 | AD48: 46090 | AE48: 1 | AF48: 24 | AG48: 127000 | AI48: 46090 | AJ48: 1 | AK48: 48 | AL48: 264000 | AN48: 46090 | AO48: 1 | AP48: 42 | AQ48: 232000 | AS48: 46090 | AT48: 1 | AU48: 24 | AV48: 125000
Y49: 46091 | Z49: 1 | AA49: 96 | AB49: 524000 | AD49: 46091 | AE49: 1 | AF49: 312 | AG49: 1638000 | AI49: 46091 | AJ49: 1 | AK49: 72 | AL49: 390000 | AN49: 46091 | AO49: 1 | AP49: 72 | AQ49: 369000 | AS49: 46091 | AT49: 1 | AU49: 33 | AV49: 177200
Y50: 46092 | Z50: 1 | AA50: 96 | AB50: 524000 | AD50: 46092 | AE50: 1 | AF50: 312 | AG50: 1651000 | AI50: 46092 | AJ50: 1 | AK50: 72 | AL50: 390000 | AN50: 46092 | AO50: 1 | AP50: 72 | AQ50: 369000 | AS50: 46092 | AT50: 1 | AU50: 24 | AV50: 125000
Y51: 46093 | Z51: 1 | AA51: 96 | AB51: 552000 | AD51: 46093 | AE51: 1 | AF51: 21 | AG51: 147000 | AI51: 46093 | AJ51: 1 | AK51: 72 | AL51: 378000 | AN51: 46093 | AO51: 1 | AP51: 61 | AQ51: 335500 | AS51: 46093 | AT51: 1 | AU51: 24 | AV51: 125000
Y52: 46094 | AD52: 46094 | AI52: 46094 | AN52: 46094 | AS52: 46094
Y53: 46095 | AD53: 46095 | AI53: 46095 | AN53: 46095 | AS53: 46095
Y54: 46096 | AA54: 0 | AD54: 46096 | AF54: 0 | AI54: 46096 | AK54: 0 | AN54: 46096 | AP54: 0 | AS54: 46096 | AU54: 0
Y55: 46097 | AD55: 46097 | AI55: 46097 | AN55: 46097 | AS55: 46097
Y56: 46098 | AD56: 46098 | AI56: 46098 | AN56: 46098 | AS56: 46098
Y57: 46099 | AD57: 46099 | AI57: 46099 | AN57: 46099 | AS57: 46099
N58: Area | O58: SPG | P58: VALUE sekarang | Q58: COST (Rp) | R58: RATIO sekarang | S58: VALUE minimal (ratio 40%) | T58: Tambahan VALUE yang dibutuhkan | Y58: 46100 | AD58: 46100 | AI58: 46100 | AN58: 46100 | AS58: 46100
N59: Banjarmasin | O59: Seri Rahmi | P59: 3695000 | Q59: 4555894 | R59: 1.23 | S59: 11389735 | T59: 7694735 | Y59: 46101 | AD59: 46101 | AI59: 46101 | AN59: 46101 | AS59: 46101
N60: Banjarmasin | O60: Khoirunisa | P60: 4200000 | Q60: 4555894 | R60: 1.08 | S60: 11389735 | T60: 7189735 | Y60: 46102 | AD60: 46102 | AI60: 46102 | AN60: 46102 | AS60: 46102
N61: Banjarmasin | O61: Herlisa | P61: 4480000 | Q61: 4555894 | R61: 1.02 | S61: 11389735 | T61: 6909735 | Y61: 46103 | AA61: 0 | AD61: 46103 | AF61: 0 | AI61: 46103 | AK61: 0 | AN61: 46103 | AP61: 0 | AS61: 46103 | AU61: 0
N62: Banjarmasin | O62: Emaral Hulda | P62: 3934000 | Q62: 4555894 | R62: 1.16 | S62: 11389735 | T62: 7455735 | Y62: 46104 | AD62: 46104 | AI62: 46104 | AN62: 46104 | AS62: 46104
N63: Balikpapan | O63: Winda | P63: 3417500 | Q63: 4556694 | R63: 1.33 | S63: 11391735 | T63: 7974235 | Y63: 46105 | AD63: 46105 | AI63: 46105 | AN63: 46105 | AS63: 46105
N64: Balikpapan | O64: Nor Hasanah | P64: 1302200 | Q64: 4556694 | R64: 3.5 | S64: 11391735 | T64: 10089535 | Y64: 46106 | AD64: 46106 | AI64: 46106 | AN64: 46106 | AS64: 46106
N65: Palangkaraya | O65: Fani Febriani | P65: 7739000 | Q65: 4424677 | R65: 0.57 | S65: 11061692 | T65: 3322692 | Y65: 46107 | AD65: 46107 | AI65: 46107 | AN65: 46107 | AS65: 46107
N66: Palangkaraya | O66: Emilia | P66: 2470000 | Q66: 4424677 | R66: 1.79 | S66: 11061692 | T66: 8591692 | Y66: 46108 | AD66: 46108 | AI66: 46108 | AN66: 46108 | AS66: 46108
N67: Tarakan | O67: Arnita | P67: 6138000 | Q67: 5442169 | R67: 0.89 | S67: 13605422 | T67: 7467422 | Y67: 46109 | AD67: 46109 | AI67: 46109 | AN67: 46109 | AS67: 46109
N68: Samarinda | O68: Fitriani | P68: 4275000 | Q68: 4683882 | R68: 1.1 | S68: 11709705 | T68: 7434705 | Y68: 46110 | AD68: 46110 | AI68: 46110 | AN68: 46110 | AS68: 46110
N69: Samarinda | O69: Desi Susanti | P69: 3747000 | Q69: 4683882 | R69: 1.25 | S69: 11709705 | T69: 7962705 | Y69: 46111 | AD69: 46111 | AI69: 46111 | AN69: 46111 | AS69: 46111
Y70: 46112 | AD70: 46112 | AI70: 46112 | AN70: 46112 | AS70: 46112
N72: Area | O72: Total VALUE sekarang | P72: Total COST | Q72: VALUE minimal (ratio 40%) | R72: Gap VALUE
N73: Balikpapan | O73: 4719700 | P73: 9113388 | Q73: 22783470 | R73: 18063770
N74: Banjarmasin | O74: 16309000 | P74: 18223576 | Q74: 45558940 | R74: 29249940
N75: Palangkaraya | O75: 10209000 | P75: 8849354 | Q75: 22123385 | R75: 11914385
N76: Samarinda | O76: 8022000 | P76: 9367764 | Q76: 23419410 | R76: 15397410
N77: Tarakan | O77: 6138000 | P77: 5442169 | Q77: 13605422 | R77: 7467422
N82: Area | O82: SPG | P82: HK MTD | Q82: Avg/day sekarang | R82: Actual MTD | S82: Value MTD | T82: Expense full bulan | U82: Estimasi actual closing | V82: Estimasi value closing | W82: Estimasi ACH closing | X82: Estimasi ratio closing
N83: Banjarmasin | O83: Seri Rahmi | P83: 18 | Q83: 72 | R83: 1296 | S83: 6972000 | T83: 4555894 | U83: 1656 | V83: 8908667 | W83: 0.719 | X83: 0.511
N84: Banjarmasin | O84: Khoirunisa | P84: 19 | Q84: 87 | R84: 1656 | S84: 9240000 | T84: 4555894 | U84: 2091 | V84: 11671579 | W84: 0.908 | X84: 0.39
N85: Banjarmasin | O85: Herlisa | P85: 20 | Q85: 92 | R85: 1848 | S85: 9768000 | T85: 4555894 | U85: 2308 | V85: 12210000 | W85: 1.002 | X85: 0.373
N86: Banjarmasin | O86: Emaral Hulda | P86: 19 | Q86: 95 | R86: 1799 | S86: 9488000 | T86: 4555894 | U86: 2274 | V86: 11984842 | W86: 0.987 | X86: 0.38
N87: Balikpapan | O87: Winda | P87: 19 | Q87: 62 | R87: 1266 | S87: 6828500 | T87: 4556694 | U87: 1576 | V87: 8625474 | W87: 0.684 | X87: 0.528
N88: Balikpapan | O88: Nor Hasanah | P88: 19 | Q88: 45 | R88: 859 | S88: 4951400 | T88: 4556694 | U88: 1084 | V88: 6254400 | W88: 0.47 | X88: 0.729
N89: Palangkaraya | O89: Fani Febriani | P89: 19 | Q89: 107 | R89: 2039 | S89: 12382000 | T89: 4424677 | U89: 2574 | V89: 15640421 | W89: 1.117 | X89: 0.283
N90: Palangkaraya | O90: Emilia | P90: 19 | Q90: 98 | R90: 1868 | S90: 11515000 | T90: 4424677 | U90: 2358 | V90: 14545263 | W90: 1.023 | X90: 0.304
N91: Tarakan | O91: Arnita | P91: 16 | Q91: 103 | R91: 1641 | S91: 9918000 | T91: 5442169 | U91: 2156 | V91: 13017375 | W91: 0.936 | X91: 0.418
N92: Samarinda | O92: Fitriani | P92: 19 | Q92: 67 | R92: 1272 | S92: 6915000 | T92: 4683882 | U92: 1607 | V92: 8734737 | W92: 0.697 | X92: 0.536
N93: Samarinda | O93: Desi Susanti | P93: 17 | Q93: 61 | R93: 1032 | S93: 5595000 | T93: 4683882 | U93: 1337 | V93: 7240588 | W93: 0.58 | X93: 0.647
N98: Metric | O98: Februari Closing | P98: Maret MTD s/d 26 | Q98: Estimasi Closing Maret
N99: HK | O99: 215 | P99: 204 | Q99: 259
N100: Actual (pcs) | O100: 14120 | P100: 16576 | Q100: 21021
N101: Average/day | O101: 65.7 | P101: 81.3 | Q101: 81.2
N102: Value | O102: 82012500 | P102: 93572900 | Q102: 118833346
N103: Expense SPG | O103: 50996251 | P103: Rp39.301.438 (prorate) | Q103: 50996251
N104: Ratio | O104: 0.622 | P104: 42,0% (fair MTD) | Q104: 42,9% (closing estimate)
I115: Area | J115: Feb HK | K115: Feb Actual | L115: Feb Avg/day | M115: Feb Value | N115: Feb Expense | O115: Feb Ratio | P115: Est. Mar HK | Q115: Est. Mar Actual | R115: Est. Mar Avg/day | S115: Est. Mar Value | T115: Est. Mar Expense | U115: Est. Mar Ratio
I116: Banjarmasin | J116: 87 | K116: 6185 | L116: 71.1 | M116: 30581000 | N116: 18223576 | O116: 0.596 | P116: 96 | Q116: 8329 | R116: 86.8 | S116: 44775088 | T116: 18223576 | U116: 0.407
I117: Balikpapan | J117: 47 | K117: 2359 | L117: 50.2 | M117: 15780000 | N117: 9113388 | O117: 0.578 | P117: 48 | Q117: 2660 | R117: 55.4 | S117: 14879874 | T117: 9113388 | U117: 0.613
I118: Palangkaraya | J118: 35 | K118: 3058 | L118: 87.4 | M118: 17958000 | N118: 8849354 | O118: 0.493 | P118: 48 | Q118: 4932 | R118: 102.8 | S118: 30185684 | T118: 8849354 | U118: 0.293
I119: Tarakan | J119: 22 | K119: 1734 | L119: 78.8 | M119: 11245000 | N119: 5442169 | O119: 0.484 | P119: 21 | Q119: 2156 | R119: 102.7 | S119: 13017375 | T119: 5442169 | U119: 0.418
I120: Samarinda | J120: 24 | K120: 784 | L120: 32.7 | M120: 6448500 | N120: 9367764 | O120: 1.453 | P120: 46 | Q120: 2944 | R120: 64 | S120: 15975325 | T120: 9367764 | U120: 0.586

Sheet SAMPLING
A1: Team leader | B1: Tahun | C1: Month | D1: Nama SPG | E1: Nama Toko | F1: Area | G1: Item type | H1: APRIL 2026 | AL1: Remarks / Cup
H2: 1 | I2: 2 | J2: 3 | K2: 4 | L2: 5 | M2: 6 | N2: 7 | O2: 8 | P2: 9 | Q2: 10 | R2: 11 | S2: 12 | T2: 13 | U2: 14 | V2: 15 | W2: 16 | X2: 17 | Y2: 18 | Z2: 19 | AA2: 20 | AB2: 21 | AC2: 22 | AD2: 23 | AE2: 24 | AF2: 25 | AG2: 26 | AH2: 27 | AI2: 28 | AJ2: 29 | AK2: 30
A3: Solehudin | B3: 2026 | C3: April | D3: Seri Rahmi | E3: Toko Ahim, H Tony ,Aini dan Farez Barokah | F3: Banjarmasin | G3: Sampling
B5: 2026 | C5: April | D5: Herlisa | E5: Toko Syahran,, H Salim, dan Saniah | F5: Banjarmasin | G5: Sampling
B7: 2026 | C7: April | D7: VACANT | F7: Banjarmasin | G7: Sampling
B9: 2026 | C9: April | F9: Banjarmasin | G9: Sampling
B11: 2026 | C11: April | D11: Nor Hasanah | E11: Toko Damai jaya | F11: Balikpapan | G11: Sampling
B13: 2026 | C13: April | D13: winda | E13: Toko Perdana | F13: Balikpapan | G13: Sampling
B15: 2026 | C15: April | D15: Fani Febriani | E15: Toko h .fathur | F15: Palangkaraya | G15: Sampling
B17: 2026 | C17: April | F17: Palangkaraya | G17: Sampling
B19: 2026 | C19: April | D19: Desi Susanti | F19: Samarinda | G19: Sampling
B21: 2026 | C21: April | D21: Fitriani | F21: Samarinda | G21: Sampling
B23: 2026 | C23: April | D23: Keni | E23: Toko Hamzah/Restu | F23: Manado | G23: Sampling
B25: 2026 | C25: April | D25: Syaloom | E25: Toko Hamzah/Restu | F25: Manado | G25: Sampling
B27: 2026 | C27: April | F27: Makassar | G27: Sampling
B29: 2026 | C29: April | F29: Makassar | G29: Sampling
B31: 2026 | C31: April | F31: Makassar | G31: Sampling
B33: 2026 | C33: April | F33: Makassar | G33: Sampling
D50: Team leader | E50: Tahun | F50: Month | G50: Nama SPG | H50: Nama Toko | I50: Area | J50: Item type | K50: Maret 2026 | AP50: Remarks / Cup
K51: 1 | L51: 2 | M51: 3 | N51: 4 | O51: 5 | P51: 6 | Q51: 7 | R51: 8 | S51: 9 | T51: 10 | U51: 11 | V51: 12 | W51: 13 | X51: 14 | Y51: 15 | Z51: 16 | AA51: 17 | AB51: 18 | AC51: 19 | AD51: 20 | AE51: 21 | AF51: 22 | AG51: 23 | AH51: 24 | AI51: 25 | AJ51: 26 | AK51: 27 | AL51: 28 | AM51: 29 | AN51: 30 | AO51: 31
D52: Solehudin | E52: 2026 | F52: Maret | G52: Seri Rahmi | H52: Toko Ahim, H Tony ,Aini dan Farez Barokah | I52: Banjarmasin | J52: Sampling | L52: 30 | M52: 30 | N52: 30 | O52: 30 | P52: 30 | Q52: 12
J53: Tumbler
D54: Solehudin | E54: 2026 | F54: Maret | G54: Khoirunisa | H54: Toko Yeyen Ibak, Mubaraq, dan Yudi | I54: Banjarmasin | J54: Sampling | L54: 30 | M54: 30 | N54: 30 | O54: 30 | P54: 30 | Q54: 12
J55: Tumbler
D56: Solehudin | E56: 2026 | F56: Maret | G56: Herlisa | H56: Toko Syahran,, H Salim, dan Saniah | I56: Banjarmasin | J56: Sampling | L56: 30 | M56: 30 | N56: 30 | O56: 30 | P56: 30 | Q56: 12
J57: Tumbler
D58: Solehudin | E58: 2026 | F58: Maret | G58: Emaral Hulda | H58: Toko PT Banyu Barokah dan Rahmah | I58: Banjarmasin | J58: Sampling | L58: 30 | M58: 30 | N58: 30 | O58: 30 | P58: 30 | Q58: 18
J59: Tumbler
D60: Solehudin | E60: 2026 | F60: Maret | G60: Nor Hasanah | H60: Toko Damai jaya | I60: Balikpapan | J60: Sampling
J61: Tumbler
D62: Solehudin | E62: 2026 | F62: Maret | G62: winda | H62: Toko Perdana | I62: Balikpapan | J62: Sampling
J63: Tumbler
D64: Solehudin | E64: 2026 | F64: Maret | G64: Fani Febriani | H64: Toko h .fathur | I64: Palangkaraya | J64: Sampling | K64: 6 | L64: 6
J65: Tumbler
D66: Solehudin | E66: 2026 | F66: Maret | G66: Emilia | H66: Toko h .fathur | I66: Palangkaraya | J66: Sampling
J67: Tumbler
D68: Solehudin | E68: 2026 | F68: Maret | G68: Arnita | H68: Toko Hamzah/Restu | I68: Tarakan | J68: Sampling
J69: Tumbler | L69: 3 | M69: 1 | N69: 1 | O69: 4
D70: Solehudin | E70: 2026 | F70: Maret | G70: Fitriani | H70: Toko Hamzah/Restu | I70: Samarinda | J70: Sampling
J71: Tumbler | N71: 2
D72: Solehudin | E72: 2026 | F72: Maret | G72: Desi Susanti | H72: Toko Hamzah/Restu | I72: Samarinda | J72: Sampling
J73: Tumbler | N73: 1 | O73: 1

Sheet PICA
A1: PICA | B1: PICA | G1: PIC | H1: STATUS
B2: PROBLEM | C2: IDENTIFIKASI | D2: CORRECTIVE | E2: ACTION | F2: DUE DATE
A3: BANJARMASIN | B3: Repeat order belum jalan karena stok warung masih banyak & banyak warung sudah ambil dari motoris, Edukasi produk belum merata, beberapa toko belum paham Extra Joss Ultimate | C3: Alokasi Gimmick Tumbler Untuk SPG, Warung masih punya stok lama, jadi menunda ambil lagi dari toko | D3: Fokus habiskan stok + buat list follow up warung yang sudah pernah ambil | E3: SPG buat daftar warung yang sudah ambil, kunjungan ulang H+2 untuk dorong tambah 6–12 can lewat toko grosir + minta nomor WA owner untuk follow up | F3: 12 Februari 2026 | G3: TL Solehudin + Seri/Nisa/Herlisa/Siti | H3: DONE
D4: Refresh product knowledge | E4: Coaching ulang 30 menit + wajib pakai “pitch 30 detik” ke setiap toko, lalu minta toko sebut ulang poin produk untuk cek pemahaman product | F4: 12 Februari 2026 | G4: TL Solehudin + Seri/Nisa/Herlisa/Siti | H4: DONE
D5: Recovery display dan foto bukti | E5: Beresin facing + taruh di posisi paling terlihat (eye level/kasir) lalu kirim foto before–after di grup | F5: 46064 | G5: TL Solehudin + Seri/Nisa/Herlisa/Siti | H5: DONE
A6: BALIKPAPAN | B6: SAMPLING DAN GIMMICK | C6: Stock Di Store Perdana | D6: * TL Alignment Dengan AM, SCO, Salesman, Dan Pihak Store Terkait OOS Di Toko | E6: *TL Sudah Koordinasi By Chat WA Dengan Team ( Mas Erizal ) di Tanggal 05 dan 06 Februari 2026 | F6: 46070 | G6: TL ABI , TEAM SALESMAN , SCO | H6: In Process
D7: * TL Mengalokasikan SPG Ke Store Yang Masih Ready Untuk Stock Extra Joss Ultimate | E7: *TL PERIODE TANGGAL 31 JANUARI - 06 FEBRUARI 2025 ,MEMBANTU LOADING PRODUCT EXTRAJOSS ULTIMATE DARI STORE STOCKIST DI MAMPANG DAN JUGA UJANG PLASTIK PONDOK LABU UNTUK DI ALOKASIKAN KE SPG YUSNITA SETIAP PAGI SEBANYAK 4 KARTON PER DAY | F7: 46070 | G7: TL Soleh , SPG WINDA | H7: In Progress
A9: TARAKAN | F9: 10 Februari 2026 | H9: DONE
A10: PALANGKARAYA | C10: Tidak Ada Space Untuk SPG Melakukan Stay | D10: *TL Propose Ke SCO Untuk Mengalokasikan SPG Ke Store Lain Dengan Traffic Yang lebih Ramai Dan Juga Dengan Type Grosir Yang Ada Space untuk SPG dapat Stay Selama 1 - 2 Jam di Store | E10: * TL Concall Dengan SCO Terkait New Store Untuk SPG | F10: 46081 | G10: TL Solehudin, SCO, SPG | H10: In Process
A11: SAMARINDA | B11: AWARENESS DAN MINAT BELI CUSTOMER MINIM | C11: Banyak Customer End User Belum Mengetahui Product Extra Joss Ultimate | D11: * SPG Melakukan Edukasi Ke Customer Dengan Menonjolkan Keunggulan Product Extra Joss Ultimate ( Highlight : Mengandung Green Coffee dan manfaat Green Coffee) pada saat sampling | E11: *SPG Searching By Google Untuk Area Yang Akan Di Sampling Seperti Bengkel, Sarana Olahraga ( GOR ) ,Pasar Modern, Kantin, Ruko Ruko , Pergudangan | F11: 46070 | G11: TL Solehudin SPG Fitriani | H11: In Process
A71: PICA | B71: PROBLEM | C71: IDENTIFIKASI | D71: CORRECTIVE | E71: ACTION | F71: DUE DATE | G71: PIC | H71: STATUS
A72: BANJARMASIN | B72: Repeat order belum maksimal | C72: Sebagian toko/retailer under grosir masih banyak stok dan belum prioritas tambah order | D72: Fokus habiskan stok berjalan dan dorong order kecil | E72: SPG cek stok aktual di toko, buat list outlet yang stoknya mulai bergerak, lalu follow up H+2 untuk order kecil 6–12 can | F72: Every day | G72: TL Soleh, Ika, Khoirunisa, Herlisa, Fatmawati, SCO/Sales | H72: In Process
A73: BANJARMASIN | B73: Konsumen lebih minat Extra Joss sachet | C73: Sebagian pelanggan menilai versi sachet lebih ekonomis dibanding kaleng | D73: Perkuat edukasi product knowledge dan benefit Extra Joss Ultimate | E73: SPG wajib pakai pitch singkat saat offering, highlight kandungan/benefit produk, lalu arahkan trial melalui sampling saat stay outlet | F73: Every day | G73: TL Soleh, All SPG Banjarmasin | H73: In Process
A74: BANJARMASIN | B74: Coverage SPG belum maksimal | C74: Fatmawati dan Herlisa ada izin sakit sehingga coverage outlet tidak full | D74: Monitoring absensi dan backup coverage outlet prioritas | E74: TL follow up kondisi SPG, atur ulang outlet prioritas, dan arahkan SPG aktif untuk bantu follow up outlet yang belum ter-cover | F74: 46163 | G74: TL Soleh, Fatmawati, Herlisa | H74: In Process
A75: BANJARMASIN | B75: Sebagian pelanggan sudah beli dari sales lain | C75: Outlet sudah pernah dilayani sales/motoris sehingga peluang closing SPG lebih terbatas | D75: Perkuat koordinasi dengan sales dan mapping outlet | E75: SPG validasi barang masuk dari sales lain, catat outlet yang sudah cover, lalu fokus ke outlet yang masih bisa repeat/order tambahan | F75: Every day | G75: TL Soleh, SPG, SCO/Sales | H75: In Process
A76: BALIKPAPAN | B76: Traffic toko rendah dan cuaca menghambat aktivitas selling | C76: Outlet tidak selalu ramai, hujan, serta jam operasional toko tidak optimal | D76: Atur jam kunjungan lebih awal dan cari titik alternatif sekitar outlet | E76: SPG visit lebih pagi, spreading ke titik ramai sekitar toko, dan update peluang closing harian ke TL | F76: Every day | G76: TL Soleh, Tiara, Jeprika | H76: In Process
A77: BALIKPAPAN | B77: Stok outlet masih tinggi | C77: Perputaran produk lambat sehingga toko belum mau tambah order | D77: Cek pergerakan stok dan dorong booking order | E77: SPG cek stok awal/akhir, tanyakan barang keluar ke toko, lalu buat jadwal follow up untuk repeat order kecil | F77: Every day | G77: TL Soleh, Tiara, Jeprika, SCO/Sales | H77: In Process
A78: BALIKPAPAN | B78: Outlet sudah di-cover sales/motoris | C78: Ruang closing SPG menjadi terbatas karena sebagian toko sudah dilayani channel lain | D78: Koordinasi outlet prioritas dengan sales/SCO | E78: TL koordinasi dengan sales untuk mapping outlet yang belum ter-cover dan arahkan SPG fokus ke outlet yang masih punya peluang closing | F78: 46164 | G78: TL Soleh, SCO/Sales, Tiara, Jeprika | H78: In Process
A79: BALIKPAPAN | B79: Sampling perlu dimaksimalkan | C79: Sampling sudah terdistribusi, namun perlu dipakai untuk dorong trial dan closing | D79: Maksimalkan sampling sebagai alat edukasi dan penawaran | E79: SPG wajib sampling ke customer potensial, dokumentasi aktivitas, dan catat respon konsumen sebagai bahan evaluasi | F79: Every day | G79: TL Soleh, Tiara, Jeprika | H79: In Process
A80: PALANGKARAYA | B80: Support sampling belum tersedia/kurang optimal | C80: Aktivitas edukasi dan trial ke customer belum maksimal tanpa sampling yang cukup | D80: Koordinasi pemenuhan sampling/tester | E80: TL follow up ketersediaan sampling ke PIC/SCO, SPG tetap edukasi produk sambil menunggu support sampling | F80: 46163 | G80: TL Soleh, Fani, Siska, SCO/PIC | H80: In Process
A81: PALANGKARAYA | B81: Banyak toko menolak order karena stok masih full | C81: Toko belum prioritas repeat karena stok lama masih tersedia | D81: Jalankan booking order dan monitoring stok | E81: SPG cek stok toko, buat estimasi kapan stok habis, lalu follow up booking order sebelum stok benar-benar habis | F81: Every day | G81: TL Soleh, Fani, Siska | H81: In Process
A82: PALANGKARAYA | B82: Minat customer belum stabil | C82: Customer lebih fokus belanja sembako/keperluan harian sehingga minuman kurang prioritas | D82: Spreading ke titik customer yang lebih sesuai | E82: SPG spreading ke area ramai seperti pasar, café, kampus, dan titik pekerja untuk mencari customer potensial | F82: Every day | G82: TL Soleh, Fani, Siska | H82: In Process
A83: PALANGKARAYA | B83: Segmentasi customer kurang sesuai | C83: Banyak customer lansia dan tidak terbiasa konsumsi minuman rasa asam | D83: Sesuaikan pendekatan sampling dengan segmentasi usia | E83: SPG fokus offering ke customer usia produktif/pekerja dan tetap edukasi secara halus ke customer lansia tanpa memaksa pembelian | F83: Every day | G83: TL Soleh, Fani, Siska | H83: In Process
A84: SAMARINDA | B84: Awareness dan minat beli customer masih perlu diperkuat | C84: Customer masih lebih fokus belanja sembako/keperluan harian dibanding minuman energi | D84: Perkuat edukasi manfaat produk saat sampling | E84: SPG wajib edukasi benefit Extra Joss Ultimate saat offering, terutama ke customer pekerja, mahasiswa, dan area aktivitas tinggi | F84: Every day | G84: TL Soleh, Fitriani, Desi Susanti | H84: In Process
A85: SAMARINDA | B85: Beberapa outlet masih menahan repeat order | C85: Stok warung/toko masih ada sehingga order tambahan belum menjadi prioritas | D85: Dorong repeat order kecil dan follow up berkala | E85: SPG cek sell out harian toko, tawarkan order kecil, dan buat reminder follow up outlet yang belum mau repeat | F85: Every day | G85: TL Soleh, Fitriani, Desi Susanti, SCO/Sales | H85: In Process
A86: SAMARINDA | B86: Outlet sudah di-cover sales/motoris | C86: Beberapa outlet sudah masuk coverage sales sehingga peluang closing SPG terbatas | D86: Mapping ulang outlet potensial | E86: TL koordinasi dengan sales/SCO untuk menentukan outlet yang masih bisa dioptimalkan SPG dan menghindari overlap coverage | F86: 46164 | G86: TL Soleh, SCO/Sales, Fitriani, Desi Susanti | H86: In Process
A87: MAKASSAR | B87: Customer belum menjadikan produk sebagai prioritas pembelian | C87: Customer cenderung fokus ke sembako/keperluan harian sehingga minuman energi kurang prioritas | D87: Perkuat edukasi dan spreading saat toko sepi | E87: SPG edukasi saat stay outlet, lalu spreading ke titik yang lebih ramai ketika stokis sepi | F87: Every day | G87: TL Soleh, Amelia | H87: In Process
A88: MAKASSAR | B88: Pembelian 12 pcs dianggap terlalu banyak untuk mendapatkan hadiah | C88: Customer keberatan dengan minimal pembelian untuk gimmick | D88: Evaluasi pendekatan gimmick dan tawarkan pembelian bertahap | E88: SPG tawarkan opsi beli bertahap/ajak pembelian kolektif, lalu catat feedback customer terkait mekanisme gimmick | F88: 46164 | G88: TL Soleh, Amelia, PIC/Sales | H88: In Process
A89: MAKASSAR | B89: Ada concern customer terkait asam lambung | C89: Customer perlu edukasi lebih hati-hati terkait konsumsi produk | D89: Edukasi product knowledge sesuai kondisi customer | E89: SPG tidak hard selling ke customer yang punya concern kesehatan, fokus edukasi umum dan arahkan ke customer yang lebih sesuai | F89: Every day | G89: TL Soleh, Amelia | H89: In Process
A90: MAKASSAR | B90: Coverage area belum maksimal | C90: Area Makassar masih hanya 1 SPG aktif sehingga pencapaian area terbatas | D90: Follow up pemenuhan manpower vacant | E90: TL follow up kandidat/SPG pengganti dan koordinasi dengan Arco/Sales agar coverage outlet bisa lebih maksimal | F90: 46166 | G90: TL Soleh, Amelia, Arco/Sales, PIC | H90: In Process
A91: MANADO | B91: Belum ada actual selling dan HK berjalan | C91: Data WIP masih 0 HK dan 0 sales sehingga aktivitas belum produktif | D91: Pastikan status running SPG dan kesiapan outlet | E91: TL follow up join/running date SPG, pastikan training, seragam, surat tugas, dan outlet sudah siap sebelum mulai report harian | F91: 46163 | G91: TL Soleh, Indriani, Bella, PIC/Admin | H91: In Process
A92: MANADO | B92: Reporting belum bisa dievaluasi | C92: Belum ada input selling, value, dan absensi berjalan | D92: Wajibkan input report sejak hari pertama running | E92: SPG wajib isi absensi, daily report, dokumentasi timestamp, dan upload struk/nota jika sudah mulai selling | F92: Hari pertama running | G92: TL Soleh, SPG Manado, Admin/PIC | H92: In Process
A98: PICA AREA BALIKPAPAN, SAMARINDA, MAKASSAR & MANADO
A99: PICA | B99: PICA | G99: PIC | H99: STATUS
B100: PROBLEM | C100: IDENTIFIKASI | D100: CORRECTIVE | E100: ACTION | F100: DUE DATE
A101: BALIKPAPAN | B101: Achievement selling rendah dan avg belum maksimal serta pencapaian spg selalu rendah | C101: Toko Perdana: harga outlet pernah Rp5.000, seharusnya Rp5.500 include gimmick min. 6 pcs. Ada motoris 3-4 orang di grosir, stok/penjualan bercampur dengan motoris, customer banyak memilih sachet, dan ada temuan harga lebih murah Rp4.000 dan SPG masih dalam 1 Grosir yang sama. | D101: SPG fokus cari toko potensial, validasi harga aktual, dan dorong selling di outlet/retailer yang belum tertutup motoris. | E101: TL minta update Yorita & Rami: traffic toko, harga aktual, stok, kendala selling/sampling, outlet yang sudah didatangi, serta dokumentasi harga murah. TL koordinasi ke SCO/AM untuk membuka outlet baru untuk spg | F101: 46202 | G101: TL Soleh, SPG Balikpapan | H101: In Process
A102: SAMARINDA | B102: Achievement selling rendah dan order perdus belum maksimal. | C102: Toko Surya Indah tidak bisa pinjam barang lagi sejak 6 Juni karena ada selisih. Traffic outlet 40+ customer, namun customer sudah punya catatan belanja dan sebagian langsung diantar pihak grosir/retailer. Barang keluar lebih banyak per pcs, bukan perdus. | D102: SPG diarahkan push outlet tambahan yang bisa transaksi langsung, manfaatkan sampling yang cukup berdampak, dan gunakan gimmick tumbler untuk bantu closing. | E102: TL kordinasi ke Area manager dan sco area samarinda untuk mencari outlet yang potensi | F102: 46202 | G102: TL Soleh, SPG Samarinda | H102: In Process
A103: MAKASSAR | B103: Selling rendah karena kendala harga toko, harga motoris, dan traffic belum dikonversi maksimal. | C103: Kariwisi Jaya traffic >30 customer, Bintang Terang traffic kurang lebih 50 customer jam 08.00-12.00, tetapi harga toko Rp7.000 sementara motoris Rp5.500. Toko Iring ada temuan harga Rp5.500 dan sales Rp4.000. Customer lebih prioritas sachet/sensitif harga; ada beban sticker/gimmick yang membuat SPG nombok. | D103: SPG fokus outlet dengan harga sudah disesuaikan, validasi harga motoris/sales, dan dorong edukasi + sampling ke retailer/pasar/terminal untuk cari repeat order. | E103: TL minta update Amelia, Nadira, Alfia: nama toko, traffic, harga jual aktual, harga motoris/sales, kendala sticker/gimmick, hasil sampling, dan outlet potensial. TL koordinasi ke SCO untuk harga outlet agar tidak kalah dari motoris. | F103: 46191 | G103: TL Soleh, SPG Makassar, Arco/SCO/Sales | H103: Done
A104: MANADO | B104: SPG belum bisa achieve minimal 1 karton dan aktivitas selling belum maksimal. | C104: SPG tidak bisa hanya stay di toko karena penjualan minim. Untuk cari omzet harus mobile ke outlet/warung kecil sekitar toko, tetapi SPG belum lancar membawa kendaraan sehingga spreading | D104: Dikarenakan SPG belum lancara membawa motor TL kordinasi ke SCO untuk replacement spg | E104: TL melakukan training pada tanggal 21 Juni 2026 atas nama Regina sebagai pengganti Dewi di area manado | F104: 46196 | G104: TL Soleh, SPG Arco area Manado | H104: Done
